Workbook

Sheet Executive Summary
B2: IMPACTLENS: GTM AND PRICING MODEL
B3: Status: DRAFT for review, 2026-09-30. Pricing is documented; GTM and revenue inputs that the docs lacked are now labelled planning assumptions on 'Planning Inputs' (owner to confirm). Colour key: blue = typed from a source · black = formula · green = linked from another sheet · yellow = key assumption to confirm.
B5: PRODUCT AND CUSTOMER
B6: Item | C6: Summary | F6: Source
B7: Product overview | C7: AI-powered media platform for impact and sustainability organisations. Field photos and video → AI analysis (captions, tags, signals, confidence, SDG mapping) → searchable, org-scoped evidence → before/after comparison, donor-ready reports and campaign copy, with scheduled delivery and public share links. | F7: PRD.md (repo root, outside docs/) §1, §4; IMPACTLENS PRICING MODEL.xlsx › A3
B8: Target customer | C8: NGOs, CSR teams and climate projects holding large volumes of unorganised field media. Users: program managers (org owners) and comms / fundraising staff; donors read shared reports. The tiers target Low / Mid / High 'impact evidence maturity' (proposed criteria on Pricing row 13). | F8: PRD.md (repo root, outside docs/) §1–§2; IMPACTLENS PRICING MODEL.xlsx › row 30
B9: Core value proposition | C9: 'Field evidence → AI insight → donor-ready reports'. Cut report and campaign drafting from hours to minutes, grounded in the org's own assets, with each org's data isolated. | F9: IMPACTLENS PRICING MODEL.xlsx › A3; PRD.md (repo root, outside docs/) §3
B10: GTM strategy | C10: DOCUMENTED: segments, value proposition, product journey, support level per tier, tier fences, a Phase 2 trigger. ASSUMED (Planning Inputs, to confirm): India-first geography, content / referral / connector / share-link channels, self-serve + founder-led motion, funnel rates, CAC ceiling, market size. HYPOTHESIS: position as the report layer for organisations that already have field media; do not lead with 'AI tagging'. | F10: GTM Strategy; ICP & Segmentation
B11: Pricing strategy | C11: Three per-organisation subscription tiers. The annual-billing price is the base; the monthly plan costs annual ÷ (1 − 17%). Tiers are fenced by limits and features (video, semantic search, share links and campaign copy from Pro; scheduled reports from Enterprise). Documented Phase 2 raises prices when SSO, RBAC, audit log, public API and verifier workflow ship. | F11: IMPACTLENS PRICING MODEL.xlsx; Pricing
B13: PRICE POINTS (linked from Pricing)
C14: Starter | D14: Pro | E14: Enterprise | F14: Comment
B15: Price, annual plan (₹ / month) | C15: =Pricing!C15 -> 2999 | D15: =Pricing!D15 -> 7999 | E15: =Pricing!E15 -> 19999 | F15: Documented.
B16: Price, monthly plan (₹ / month) | C16: =Pricing!C17 -> 3613 | D16: =Pricing!D17 -> 9637 | E16: =Pricing!E17 -> 24095 | F16: Calculated: annual ÷ (1 − 17%).
B17: Price, annual plan (USD / month) | C17: =Pricing!C16 -> 31 | D17: =Pricing!D16 -> 83 | E17: =Pricing!E16 -> 208 | F17: Calculated at the workbook's FX rate; indicative.
B18: Phase 2 price, low (₹ / month) | C18: =Pricing!C71 -> 4000 | D18: =Pricing!D71 -> 12000 | E18: =Pricing!E71 -> 29000 | F18: Documented; not in effect.
B19: Phase 2 price, high (₹ / month) | C19: =Pricing!C72 -> 5000 | D19: =Pricing!D72 -> 15000 | E19: =Pricing!E72 -> 39000 | F19: Documented; not in effect.
B20: Gross margin, as modelled | C20: =Pricing!C57 -> 0.85561854 | D20: =Pricing!D57 -> 0.65245656 | E20: =Pricing!E57 -> 0.48747437 | F20: Calculated; cost floor at full allowance use.
B21: Gross margin, published Cloudinary price | C21: =Pricing!C63 -> 0.84227735 | D21: =Pricing!D63 -> 0.62744704 | E21: =Pricing!E63 -> 0.45746521 | F21: Calculated; see contradiction O-01.
B22: Gross margin, all-video upper bound | C22: =Pricing!C66 -> 0.84227735 | D22: =Pricing!D66 -> 0.064876721 | E22: =Pricing!E66 -> -0.66759105 | F22: Calculated stress case; see O-06.
B24: KEY ASSUMPTIONS TO CONFIRM
B25: Cloudinary cost per credit | C25: =Pricing!$C$51 -> 34 | D25: Model uses this; published price implies a higher figure (O-01).
B26: AI cost per vision analysis (₹) | C26: =Pricing!$C$52 -> 0.9 | D26: Unmeasured assumption.
B27: Annual billing discount | C27: =Pricing!$C$7 -> 0.17 | D27: Documented.
B28: USD → INR rate | C28: =Pricing!$C$8 -> 96.07 | D28: Documented, undated.
B29: Organisations for Phase 2 pricing | C29: 50 | D29: Documented trigger (plus API pilot and funder-verification pilots).
B31: KEY METRICS / KPIs
B32: KPI | C32: Target | F32: Source / status
B33: Time to a searchable asset | C33: Under 30 s per image | F33: Documented: PRD.md (repo root, outside docs/) §6
B34: Reports citing ≥ 3 real assets | C34: 100% | F34: Documented: PRD.md (repo root, outside docs/) §6 (not enforced today)
B35: Cross-tenant reads / writes | C35: 0 | F35: Documented: PRD.md (repo root, outside docs/) §6
B36: Paying organisations (Phase 2 trigger) | C36: 50 | F36: Documented: IMPACTLENS PRICING MODEL.xlsx › D72
B37: CAC, conversion, churn, NRR | C37: ="Sign-up → paid "&TEXT('Planning Inputs'!$D$23,"0.0%")&"; CAC ≤ ₹"&TEXT('Revenue Model'!C67,"#,##0")&" / ₹"&TEXT('Revenue Model'!D67,"#,##0")&" / ₹"&TEXT('Revenue Model'!E67,"#,##0")&"; churn ≤ "&TEXT('Revenue Model'!C62,"0.0%")&" / "&TEXT('Revenue Model'!D62,"0.0%")&" / "&TEXT('Revenue Model'!E62,"0.0%")&" a month; NRR "&TEXT('Revenue Model'!C88,"0%") -> Sign-up → paid 10.1%; CAC ≤ ₹30,792 / ₹62,628 / ₹1,75,482; churn ≤ 3.0% / 1.5% / 0.7% a month; NRR 98% | F37: Assumed targets (Planning Inputs; Revenue Model section D).
B39: HOW COMPLETE IS THE EVIDENCE? (counts from 'Assumptions & Sources')
B40: Type | C40: Items
B41: Documented | C41: =COUNTIF('Assumptions & Sources'!$I$6:$I$52,"Documented") -> 27
B42: Calculated | C42: =COUNTIF('Assumptions & Sources'!$I$6:$I$52,"Calculated") -> 8
B43: Assumption | C43: =COUNTIF('Assumptions & Sources'!$I$6:$I$52,"Assumption") -> 8
B44: Hypothesis | C44: =COUNTIF('Assumptions & Sources'!$I$6:$I$52,"Hypothesis") -> 3
B45: Unfilled | C45: =COUNTIF('Assumptions & Sources'!$I$6:$I$52,"TBD") -> 0
B46: Contradicted | C46: =COUNTIF('Assumptions & Sources'!$I$6:$I$52,"Contradicted") -> 1
B47: Open items (contradictions and gaps) | C47: =COUNTA('Open Items'!B6:B21) -> 16
B49: SHEETS
B50: Executive Summary | C50: This page.
B51: ICP & Segmentation | C51: Segments, pain points, decision makers, tier fit.
B52: GTM Strategy | C52: Strategy elements, journey and conversion stages, phasing, KPIs.
B53: Pricing | C53: Inputs, tiers, entitlements, unit economics, Phase 2, discounts / add-ons.
B54: Revenue Model | C54: Per-customer economics, scale arithmetic, blank scenario builder.
B55: Competitive Positioning | C55: 25 competitors with sources, prices and differentiation.
B56: Assumptions & Sources | C56: Register of every input with source and status.
B57: Open Items | C57: Contradictions and missing information.
B58: Planning Inputs | C58: Every assumption the docs lacked: funnel, churn, CAC, costs, market, add-ons, segment scores.

Sheet ICP & Segmentation
B2: ICP & SEGMENTATION
B3: Segments are taken from PRD.md §2 and the problem statement, plus hypotheses from docs/COMPETITIVE-LANDSCAPE.md §3. Buying triggers and decision makers were not in the docs; they are filled as Assumptions (no customer interviews yet). Attractiveness is a weighted score from 'Planning Inputs' section 9. Filter on the Status column.
B5: A · CUSTOMER SEGMENTS
B6: ID | C6: Customer segment | D6: Customer type | E6: Characteristics (documented) | F6: Pain points | G6: Needs / use cases | H6: Buying triggers | I6: Decision makers | J6: Attractiveness | K6: Source | L6: Confidence | M6: Status
B7: S1 | C7: Program teams at NGOs and impact organisations | D7: Buyer and user (persona: 'Program manager', the org owner) | E7: Collects large volumes of photos and video from plantings, installs, cleanups and classrooms. Each org is its own workspace; joining an existing org needs an owner's invite code. | F7: Media sits unorganised. Proving impact to donors means someone manually sorting files, writing captions, finding before/after pairs and drafting reports. The evidence exists, but nobody can search it or cite it. | G7: Upload field media and organise it by project; show progress over time (map, timeline, SDG goals, health score); before/after comparison; keep the org's data isolated. | H7: Donor or grant report deadline; a new funder asking for photo evidence; annual-report season. | I7: Program manager (org owner) chooses; executive director approves spend at Pro and above (assumption). | J7: =TEXT('Planning Inputs'!$H$75,"0.00")&" / 5 (rank "&'Planning Inputs'!$I$75&" of 6)" -> 4.30 / 5 (rank 1 of 6) | K7: PRD.md (repo root, outside docs/) §1, §2, §3 | L7: Documented | M7: Documented
B8: S2 | C8: Comms and fundraising teams | D8: User (persona: 'Comms / fundraising', a member) | E8: Draft donor reports and social campaigns from the org's own assets. | F8: Same as S1; specifically finding the right shot fast and drafting reports and campaigns by hand. | G8: Semantic search over media; impact, summary, campaign and comparison reports (1–4 variants, choice of tone); campaign copy per platform (Instagram, X, LinkedIn, newsletter). | H8: Fundraising campaign or annual report; a social-media push around an event. | I8: Influencer, not a budget holder: head of comms recommends, executive director approves (assumption). | J8: =TEXT('Planning Inputs'!$H$76,"0.00")&" / 5 (rank "&'Planning Inputs'!$I$76&" of 6)" -> 3.75 / 5 (rank 3 of 6) | K8: PRD.md (repo root, outside docs/) §2 | L8: Documented | M8: Documented
B9: S3 | C9: Corporate CSR and sustainability teams | D9: Buyer (named as an intended user of the product) | E9: CSR teams are named in the problem statement. The competitor research found BNZ Impact naming 'Corporates & CSR Teams' as its buyers and selling geo-tagged, verified evidence. | F9: Need evidence that can be verified. ImpactLens today has no GPS, no content hash and a manual 'verified' flag, so it is under-serving this segment (memo §1, §3). | G9: Verifiable evidence packs; funder-facing reporting. | H9: Annual CSR report and board review of Section 135 spend; audits of implementation partners. | I9: CSR head or sustainability lead; procurement signs Enterprise contracts (assumption). | J9: =TEXT('Planning Inputs'!$H$77,"0.00")&" / 5 (rank "&'Planning Inputs'!$I$77&" of 6)" -> 3.55 / 5 (rank 4 of 6) | K9: PRD.md (repo root, outside docs/) §1; docs/COMPETITIVE-LANDSCAPE.md §3 (verified: BNZ Impact page, 2026-09-29) | L9: Medium | M9: Hypothesis
B10: S4 | C10: Governments and sustainability organisations | D10: Named in the hackathon brief | E10: The brief lists 'NGOs, governments, and sustainability organizations' as generators of field media. | F10: As the brief states: manually organising, analysing and verifying media is time-consuming and hard to scale. | G10: Scheme monitoring evidence with data-residency and procurement (tender / GeM) rules (assumption). | H10: Scheme review cycles and audit findings. | I10: Department officer through a tender; long cycle (assumption). | J10: =TEXT('Planning Inputs'!$H$78,"0.00")&" / 5 (rank "&'Planning Inputs'!$I$78&" of 6)" -> 2.35 / 5 (rank 6 of 6) | K10: Hackathon brief (Problem Statement 02; supplied in session, not stored in the repo) | L10: Low | M10: Assumption
B11: S5 | C11: Small and mid NGOs with a photo backlog and no M&E staff | D11: Buyer (proposed gap segment) | E11: Has a library of field photos and video but no monitoring-and-evaluation team. | F11: The priced tools found aim at teams that collect data (capture, forms) or fund programs (M&E suites): no priced plan in the $30–$100 range turns an existing photo library into cited reports. | G11: Turn an existing media library into searchable, cited, donor-ready evidence at low cost. | H11: First institutional grant, or a donor asking for evidence the team cannot find. | I11: Founder or executive director: one decision maker (assumption). | J11: =TEXT('Planning Inputs'!$H$79,"0.00")&" / 5 (rank "&'Planning Inputs'!$I$79&" of 6)" -> 3.85 / 5 (rank 2 of 6) | K11: docs/COMPETITIVE-LANDSCAPE.md §1, §3 (calculated from verified competitor prices) | L11: Low | M11: Hypothesis
B12: S6 | C12: Funder-verification-driven organisations (Phase 2) | D12: Buyer (future) | E12: Multi-funder programs that need verifier sign-off, SSO / RBAC and an audit trail. | F12: Need evidence-grade compliance (per the Phase 2 rationale). | G12: Verification workflow, immutable audit log, public API, multi-funder dashboards, BYOC storage, 99.9% uptime SLA. | H12: Documented trigger for Phase 2 pricing: 50 paying orgs + public API pilot + funder-verification pilots closed. | I12: Funder's M&E lead together with the org's executive director; verifier sign-off (assumption). | J12: =TEXT('Planning Inputs'!$H$80,"0.00")&" / 5 (rank "&'Planning Inputs'!$I$80&" of 6)" -> 3.10 / 5 (rank 5 of 6) | K12: IMPACTLENS PRICING MODEL.xlsx › rows 71–77 | L12: Medium | M12: Documented
B13: S7 | C13: Donors and external stakeholders | D13: Reader, not a buyer | E13: Reads a report through a public read-only link, with no account. | F13: Cannot see the underlying evidence: the share page and its report show text only (memo U8). | G13: Read a report through a public link; ideally see the evidence behind it. | H13: n/a: does not purchase. | I13: n/a | J13: n/a | K13: PRD.md (repo root, outside docs/) §2; docs/COMPETITIVE-LANDSCAPE.md U8 | L13: Medium | M13: Documented
B15: B · TIER FIT (how the documented pricing tiers map to customers)
C16: Tier | D16: Impact-evidence maturity | E16: Price (₹ / month, annual plan) | F16: Segment fit | G16: Status
C17: Starter | D17: =Pricing!C13 -> Low | E17: =Pricing!C15 -> 2999 | F17: Most likely S5 and small S1 teams (inference from 'Low maturity' and the 3-seat, 250-asset limits). | G17: Assumption
C18: Pro | D18: =Pricing!D13 -> Mid | E18: =Pricing!D15 -> 7999 | F18: S1 and S2 teams that need search, campaign copy and share links (inferred from the feature fences). | G18: Assumption
C19: Enterprise | D19: =Pricing!E13 -> High | E19: =Pricing!E15 -> 19999 | F19: S3 and S6 (multi-org, scheduled reports, dedicated support; verification features arrive in Phase 2). | G19: Assumption
B20: Only the maturity label is documented for each tier. The mapping to segments is my inference and is marked Assumption. 'Maturity' has no definition (Open Items O-11).

Sheet GTM Strategy
B2: GTM STRATEGY
B3: Documented rows come from the PRD and the pricing model. Channels, marketing, sales channel, geography, funnel volumes and GTM KPI targets did not exist in the docs; they are now filled from 'Planning Inputs' and marked Assumption. Hypothesis rows come from docs/COMPETITIVE-LANDSCAPE.md.
B5: A · STRATEGY ELEMENTS
B6: Element | C6: Detail | D6: Status | E6: Source | F6: Note
B7: Target segments | C7: Program managers (org owners) and comms/fundraising staff at NGOs, CSR teams and climate projects. Donors read shared reports but do not buy. | D7: Documented | E7: PRD.md (repo root, outside docs/) §2 | F7: See ICP & Segmentation.
B8: Value proposition | C8: 'Field evidence → AI insight → donor-ready reports'. Cut report and campaign drafting from hours to minutes, grounded in the org's own assets, with each org's data strictly isolated. | D8: Documented | E8: IMPACTLENS PRICING MODEL.xlsx › A3; PRD.md (repo root, outside docs/) §3
B9: Positioning | C9: 'The report layer for organisations that already have field photos and video: turn a media library into cited, donor-ready evidence.' Do not position as capture; do not lead with 'AI tagging'. | D9: Hypothesis | E9: docs/COMPETITIVE-LANDSCAPE.md §3 | F9: Needs testing with real buyers. Reason: Cloudinary's Plus plan already lists auto-tagging.
B10: Acquisition channels | C10: 1) Content / SEO: donor-report, CSR-report and before/after templates. 2) Referrals from CSR implementation agencies and NGO capacity-building networks. 3) KoboToolbox / CommCare import connector as a partner listing (memo U12). 4) Public share links and the embeddable report widget as a viral loop (U8). | D10: Assumption | E10: — | F10: Proposed. Volume needed is in the funnel below (row 23). Test the channel mix in the first 90 days.
B11: Marketing approach | C11: Product-led: 14-day free trial plus report templates; one customer case study a month built from consented evidence; webinars with NGO networks ahead of annual-report and CSR-filing season (Apr–Jun, the first quarter of the Indian financial year). | D11: Assumption | E11: —
B12: Sales channel | C12: ='Planning Inputs'!$D$10 -> Self-serve trial and web checkout for Starter and Pro; founder-led sales for Enterprise, CSR and funder buyers. No resellers in year 1. | D12: Assumption | E12: —
B13: Sales motion | C13: Support scales by tier: Email (Starter), Email + Chat (Pro), Dedicated + SLA (Enterprise). Whether Starter/Pro are self-serve and Enterprise is sales-led is an inference, not documented. | D13: Assumption | E13: IMPACTLENS PRICING MODEL.xlsx › D69:H69 | F13: Confirm the motion before building the funnel.
B14: Distribution channel (product) | C14: A web application. Deployment target is undecided: Caddy on a VM, or a Vercel-style host. This affects headers, proxy trust and cron. | D14: Documented | E14: PRD.md (repo root, outside docs/) §7 | F14: Open question in the PRD.
B15: Delivery channels inside the product | C15: Scheduled reports by email, run-summary posts to Slack, public read-only share links, CSV export, print-to-PDF. | D15: Documented | E15: PRD.md (repo root, outside docs/) §4 (F8, F10, F11)
B16: Partner / channel ideas | C16: Embeddable public report widget on partner sites (U8); import connectors from Fulcrum, CommCare and KoboToolbox instead of building capture (U12); WhatsApp delivery of scheduled reports (U13). | D16: Hypothesis | E16: docs/COMPETITIVE-LANDSCAPE.md §5 | F16: Proposed, not decided. Connector APIs and terms not yet checked.
B17: Geographic strategy | C17: ='Planning Inputs'!$D$8 -> India first: INR billing with GST invoices and Razorpay checkout. English-speaking international NGOs billed in USD (indicative prices on Pricing) once a USD checkout exists. | D17: Assumption | E17: IMPACTLENS PRICING MODEL.xlsx › D7; docs/competitors.csv | F17: Resolves Open Items O-04 as a planning assumption; owner to confirm.
B18: Pricing as a GTM lever | C18: Tier fences: video analysis, semantic search, share links and campaign copy start at Pro; scheduled reports start at Enterprise. A 17% discount rewards annual billing. | D18: Documented | E18: IMPACTLENS PRICING MODEL.xlsx › Tier Feature Overview | F18: See Pricing.
B19: Pre-conditions before selling to funder-facing / verification buyers | C19: Provenance hash + GPS (U1), enforced report citations (U2), and enforceable plan limits (U3). | D19: Hypothesis | E19: docs/COMPETITIVE-LANDSCAPE.md §5 (P0) | F19: A recommendation from the audit, not a decision.
B21: B · CUSTOMER JOURNEY AND CONVERSION STAGES (volumes over 12 months, from Planning Inputs section 2)
B22: Stage | C22: What happens (documented product behaviour) | D22: Volume (12 months) | E22: Conversion to next stage | F22: Documented target / source
B23: 1 · Awareness | C23: Content / SEO, partner referrals, connector listing and share links (row 10). | D23: =D24/'Planning Inputs'!$D$16 -> 22772.552 | E23: =IF(AND(ISNUMBER(D23),ISNUMBER(D24),N(D23)>0),D24/D23,"n/a") -> 0.025 | F23: ="Target: "&TEXT(D23,"#,##0")&" site visits in 12 months at "&TEXT('Planning Inputs'!$D$16,"0.0%")&" visit → sign-up." -> Target: 22,773 site visits in 12 months at 2.5% visit → sign-up.
B24: 2 · Sign-up | C24: Email + password sign-up. Creating an org, or joining an existing one with the owner's invite code (F1). | D24: ='Planning Inputs'!$D$14*((1+'Planning Inputs'!$D$15)^12-1)/'Planning Inputs'!$D$15 -> 569.31379 | E24: =IF(AND(ISNUMBER(D24),ISNUMBER(D25),N(D24)>0),D25/D24,"n/a") -> 0.7 | F24: PRD.md (repo root, outside docs/) §4 F1
B25: 3 · First upload | C25: Upload up to 10 MB in the browser, add an external URL, or generate an image with AI (F2). | D25: =D24*'Planning Inputs'!$D$17 -> 398.51966 | E25: =IF(AND(ISNUMBER(D25),ISNUMBER(D26),N(D25)>0),D26/D25,"n/a") -> 0.95 | F25: PRD.md (repo root, outside docs/) §4 F2
B26: 4 · First analysis | C26: AI captions, tags, signals, confidence, SDG mapping; video by frame sampling (F3). | D26: =D25*'Planning Inputs'!$D$18 -> 378.59367 | E26: =IF(AND(ISNUMBER(D26),ISNUMBER(D27),N(D26)>0),D27/D26,"n/a") -> 0.7 | F26: Target: under 30 s from upload to a searchable, tagged image (PRD.md (repo root, outside docs/) §6)
B27: 5 · Value moment | C27: Search, filter, before/after comparison, project map / timeline / health score (F4–F7). | D27: =D26*'Planning Inputs'!$D$19 -> 265.01557 | E27: =IF(AND(ISNUMBER(D27),ISNUMBER(D28),N(D27)>0),D28/D27,"n/a") -> 0.6 | F27: Activated = at least one analysed asset and one generated report (proposed definition; KPI row 49).
B28: 6 · Report or campaign | C28: Generate impact, summary, campaign or comparison reports; campaign copy per platform (F8, F9). | D28: =D27*'Planning Inputs'!$D$20 -> 159.00934 | E28: =IF(AND(ISNUMBER(D28),ISNUMBER(D29),N(D28)>0),D29/D28,"n/a") -> 0.6 | F28: Target: 100% of reports cite at least 3 real org assets (PRD.md (repo root, outside docs/) §6; enforcement is not built, memo U2)
B29: 7 · Share or schedule | C29: Public read-only share link; scheduled email and Slack delivery (F10, F11). | D29: =D28*'Planning Inputs'!$D$21 -> 95.405606 | E29: =IF(AND(ISNUMBER(D29),ISNUMBER(D30),N(D29)>0),D30/D29,"n/a") -> 0.6 | F29: PRD.md (repo root, outside docs/) §4
B30: 8 · Paid conversion / upgrade | C30: Proposed: 14-day opt-in free trial with Pro features (25 analyses, 2 credits), then self-serve checkout for Starter / Pro or a sales call for Enterprise. | D30: =D29*'Planning Inputs'!$D$22 -> 57.243363 | E30: =IF(AND(ISNUMBER(D30),ISNUMBER(D31),N(D30)>0),D31/D30,"n/a") -> 0.90382846 | F30: ="Target: "&TEXT(D30,"0")&" new paying orgs in 12 months = "&TEXT('Planning Inputs'!$D$23,"0.0%")&" of sign-ups (opt-in trial benchmark 8–22%, median 14%)." -> Target: 57 new paying orgs in 12 months = 10.1% of sign-ups (opt-in trial benchmark 8–22%, median 14%).
B31: 9 · Renewal and expansion | C31: Annual plans; Phase 2 repricing when SSO / RBAC / audit log / API ship. | D31: ='Revenue Model'!O48 -> 51.738181 | E31: n/a | F31: Row 31 volume = paying orgs still active at M12 (Revenue Model O48), so E30 is 12-month logo retention.
B32: Volumes are calculated from Planning Inputs section 2; change the sign-up or stage rates there.
B34: C · PHASING
B35: Phase | C35: What it means | D35: Status | E35: Trigger / gate | F35: Source
B36: Phase 1 (now) | C36: Phase 1 subscription prices (Starter / Pro / Enterprise). The PRD lists the product as built and hardening in progress. | D36: Documented | E36: ="In effect from "&TEXT('Planning Inputs'!$D$9,"d mmm yyyy")&" (planning start)." -> In effect from 1 Oct 2026 (planning start). | F36: IMPACTLENS PRICING MODEL.xlsx; PRD.md (repo root, outside docs/) header
B37: Before funder-facing sales | C37: Provenance hash + GPS, enforced citations, enforceable plan limits (P0 in the memo). | D37: Hypothesis | E37: Recommendation; not scheduled. | F37: docs/COMPETITIVE-LANDSCAPE.md §5
B38: Phase 2 | C38: SSO, RBAC, immutable audit log, public API, verifier workflow, BYOC storage, 99.9% uptime SLA; prices rise (see Pricing section 5). | D38: Documented | E38: ="50 paying orgs + public API pilot + funder-verification pilots closed. Modelled 50-org date: "&IF(ISNUMBER('Revenue Model'!C92),TEXT('Revenue Model'!C92,"mmm yyyy"),'Revenue Model'!C92)&"." -> 50 paying orgs + public API pilot + funder-verification pilots closed. Modelled 50-org date: Sep 2027. | F38: IMPACTLENS PRICING MODEL.xlsx › D71:D77
B40: D · KPIs (documented targets first; proposed GTM metrics have NO targets in the docs)
B41: KPI | C41: Definition | D41: Type | E41: Target | F41: Source
B42: Time to a searchable asset | C42: Time from upload to a searchable, tagged asset. | D42: Documented | E42: Under 30 s per image | F42: PRD.md (repo root, outside docs/) §6
B43: Reports citing real assets | C43: Share of generated reports that cite at least 3 real org assets. | D43: Documented | E43: 100% | F43: PRD.md (repo root, outside docs/) §6 (not measured or enforced today)
B44: Cross-tenant reads / writes | C44: Count found by the e2e scoping suite. | D44: Documented | E44: 0 | F44: PRD.md (repo root, outside docs/) §6
B45: Dashboard load | C45: Dashboard interactive time on the seeded database. | D45: Documented | E45: Under 2 s | F45: PRD.md (repo root, outside docs/) §5
B46: Paying organisations | C46: Count of paying orgs; also the Phase 2 pricing trigger. | D46: Documented | E46: 50 (trigger) | F46: IMPACTLENS PRICING MODEL.xlsx › D72
B47: Gross margin by tier | C47: Gross profit ÷ price at the tier's cost floor. | D47: Calculated | E47: ="≥ "&TEXT('Revenue Model'!O56,"0.0%")&" blended at M12 (scenario); floor "&TEXT(MIN(Pricing!C57:E57),"0.0%")&" (Enterprise)." -> ≥ 64.1% blended at M12 (scenario); floor 48.7% (Enterprise). | F47: Pricing section 4
B48: Sign-up → first upload rate | C48: Share of new orgs that upload media. | D48: Assumption | E48: =TEXT('Planning Inputs'!$D$17,"0%")&" of new orgs upload within the trial." -> 70% of new orgs upload within the trial. | F48: Target derived from Planning Inputs (not in the docs).
B49: Activation rate | C49: Share of orgs with at least one analysed asset and one generated report. | D49: Assumption | E49: =TEXT(D28/D24,"0.0%")&" of sign-ups (analysed asset + report)." -> 27.9% of sign-ups (analysed asset + report). | F49: Target derived from Planning Inputs (not in the docs).
B50: Free/trial → paid conversion | C50: Depends on a trial or free tier existing (none documented). | D50: Assumption | E50: =TEXT('Planning Inputs'!$D$23,"0.0%")&" of sign-ups (benchmark median 14%)." -> 10.1% of sign-ups (benchmark median 14%). | F50: Target derived from Planning Inputs (not in the docs).
B51: CAC and payback | C51: Cost to acquire a paying org and months to recover it. | D51: Assumption | E51: ="Payback ≤ 12 / 12 / 18 months → CAC ≤ ₹"&TEXT('Revenue Model'!C67,"#,##0")&" / ₹"&TEXT('Revenue Model'!D67,"#,##0")&" / ₹"&TEXT('Revenue Model'!E67,"#,##0")&" (Starter / Pro / Enterprise)." -> Payback ≤ 12 / 12 / 18 months → CAC ≤ ₹30,792 / ₹62,628 / ₹1,75,482 (Starter / Pro / Enterprise). | F51: Target derived from Planning Inputs (not in the docs).
B52: Logo churn and net revenue retention | C52: Share of orgs lost per period; revenue retained incl. upgrades. | D52: Assumption | E52: ="Churn ≤ "&TEXT('Revenue Model'!C62,"0.0%")&" / "&TEXT('Revenue Model'!D62,"0.0%")&" / "&TEXT('Revenue Model'!E62,"0.0%")&" a month; NRR ≥ "&TEXT('Revenue Model'!C88,"0%")&" (12-month, scenario)." -> Churn ≤ 3.0% / 1.5% / 0.7% a month; NRR ≥ 98% (12-month, scenario). | F52: Target derived from Planning Inputs (not in the docs).

Sheet Pricing
B2: PRICING
B3: Source of truth: docs/IMPACTLENS PRICING MODEL.xlsx (sheet 'ImpactLens Pricing'). Blue = typed from a document · black = formula · green = linked from another sheet. Section 6 add-ons, overage, discounts and trial are planning assumptions from 'Planning Inputs'. All prices in INR; USD is indicative at the rate below.
B5: 1 · GLOBAL INPUTS
B6: Input | C6: Value | F6: Source / status
B7: Annual billing discount | C7: 0.17 | F7: Documented: IMPACTLENS PRICING MODEL.xlsx › ImpactLens Pricing › D6
B8: USD → INR rate | C8: 96.07 | F8: Documented: IMPACTLENS PRICING MODEL.xlsx › D8 (marked editable). Date and source of the rate are not documented.
B9: Primary currency | C9: INR (₹); USD indicative | F9: Documented: IMPACTLENS PRICING MODEL.xlsx › D7. Target geography is not documented (see Open Items O-04).
B11: 2 · TIERS AND PRICE (per organisation per month; the workbook's COGS block is 'per org / month')
B12: Line | C12: Starter | D12: Pro | E12: Enterprise | F12: Source / note
B13: Impact Evidence Maturity Level | C13: Low | D13: Mid | E13: High | F13: Criteria (proposed, closes Open Items O-11 as an assumption): Low = one programme, media in shared drives, no M&E staff, ≤ 250 assets; Mid = several projects, regular reports to 1–5 funders, up to 5,000 assets; High = multiple programmes or orgs, funder verification or scheduled reporting, an M&E function. Proposed from the tier limits (assumption).
B14: Target customer (as documented) | C14: Low-maturity programs | D14: Mid-maturity programs | E14: High-maturity programs | F14: Only the maturity label is documented; there is no firmographic definition (ICP sheet, section B).
B15: Price: annual plan (₹ / month) | C15: 2999 | D15: 7999 | E15: 19999 | F15: Documented: IMPACTLENS PRICING MODEL.xlsx › D31:F31 (marked star input; 'per-month charges billed annually').
B16: Price: annual plan (USD / month, indicative) | C16: =ROUND(C15/$C$8,0) -> 31 | D16: =ROUND(D15/$C$8,0) -> 83 | E16: =ROUND(E15/$C$8,0) -> 208 | F16: Calculated: ₹ price ÷ USD→INR rate. Mirrors the source workbook's row 32.
B17: Price: monthly plan (₹ / month) | C17: =ROUND(C15/(1-$C$7),0) -> 3613 | D17: =ROUND(D15/(1-$C$7),0) -> 9637 | E17: =ROUND(E15/(1-$C$7),0) -> 24095 | F17: Calculated with the source formula: annual price ÷ (1 − discount). Source: D11 and H34:J34.
B18: Billed per year: annual plan (₹) | C18: =C15*12 -> 35988 | D18: =D15*12 -> 95988 | E18: =E15*12 -> 239988 | F18: Calculated (× 12).
B19: Billed per year: monthly plan (₹) | C19: =C17*12 -> 43356 | D19: =D17*12 -> 115644 | E19: =E17*12 -> 289140 | F19: Calculated (× 12).
B20: Saving from billing annually (₹ / year) | C20: =C19-C18 -> 7368 | D20: =D19-D18 -> 19656 | E20: =E19-E18 -> 49152 | F20: Calculated. Source workbook row 40 (small differences are rounding of the monthly price).
B21: Effective annual discount | C21: =C20/C19 -> 0.16994188 | D21: =D20/D19 -> 0.16996991 | E21: =E20/E19 -> 0.16999377 | F21: Calculated: equals the input discount by construction (it is not independent evidence of price sensitivity).
B22: Billing frequency | C22: Annual (shown per month) or monthly | D22: Annual (shown per month) or monthly | E22: Annual (shown per month) or monthly | F22: Documented: IMPACTLENS PRICING MODEL.xlsx › D9:D10. The monthly plan is priced higher; there is no free tier or trial in the docs.
B23: Support | C23: Email | D23: Email + Chat | E23: Dedicated + SLA | F23: Documented: IMPACTLENS PRICING MODEL.xlsx › D69:H69. The SLA terms are not defined ('99.9% uptime SLA' appears only as a Phase 2 item).
B25: 3 · WHAT EACH TIER INCLUDES (usage limits and features)
B26: Feature / limit | C26: Starter | D26: Pro | E26: Enterprise | F26: Source / note
B27: Organizations (multi-tenant) | C27: 1 | D27: 1 | E27: Unlimited | F27: Documented: IMPACTLENS PRICING MODEL.xlsx › Tier Feature Overview.
B28: Team seats | C28: 3 | D28: 10 | E28: Unlimited | F28: Documented: IMPACTLENS PRICING MODEL.xlsx › Tier Feature Overview.
B29: Media assets in library | C29: 250 | D29: 5,000 | E29: Unlimited | F29: Documented: IMPACTLENS PRICING MODEL.xlsx › Tier Feature Overview. Limits are not enforced in the product today (memo U3).
B30: Video analysis (ffmpeg frame sampling) | C30: — | D30: ✔ | E30: ✔ | F30: Documented: IMPACTLENS PRICING MODEL.xlsx › Tier Feature Overview.
B31: Before/after comparison + impact score | C31: 5 / mo | D31: 100 / mo | E31: Unlimited | F31: Documented: IMPACTLENS PRICING MODEL.xlsx › Tier Feature Overview. Comparison cost is not in COGS (Open Items O-09).
B32: Semantic search (LLM-scored) | C32: — | D32: ✔ | E32: ✔ | F32: Documented: IMPACTLENS PRICING MODEL.xlsx › Tier Feature Overview. Shown as a bare tick, but the COGS line assumes about 300 (Pro) and 1,000 (Enterprise) searches a month: see section 4.
B33: Saved searches | C33: 3 | D33: 50 | E33: Unlimited | F33: Documented: IMPACTLENS PRICING MODEL.xlsx › Tier Feature Overview.
B34: Impact / summary reports (LLM) | C34: 3 / mo | D34: 30 / mo | E34: 150 / mo | F34: Documented: IMPACTLENS PRICING MODEL.xlsx › Tier Feature Overview.
B35: Report variants (4 angles) + clone | C35: — | D35: ✔ | E35: ✔ | F35: Documented: IMPACTLENS PRICING MODEL.xlsx › Tier Feature Overview.
B36: Campaign copy (IG / X / LinkedIn / newsletter) | C36: — | D36: ✔ | E36: ✔ | F36: Documented: IMPACTLENS PRICING MODEL.xlsx › Tier Feature Overview. Cost not in COGS.
B37: Scheduled reports + email delivery (cron) | C37: — | D37: — | E37: ✔ | F37: Documented: IMPACTLENS PRICING MODEL.xlsx › Tier Feature Overview. Cost not in COGS.
... B41: SSO / RBAC / audit log | C41: — | D41: — | E41: Phase 2 | F41: Documented: IMPACTLENS PRICING MODEL.xlsx › Tier Feature Overview. Listed on the Enterprise tier but not built (Open Items O-02).
B42: VLM analysis: images (per month) | C42: =C49 -> 100 | D42: =D49 -> 1000 | E42: =E49 -> 5000 | F42: Documented: IMPACTLENS PRICING MODEL.xlsx › D55:H55. Linked to section 4.
B43: Cloudinary CDN credits included (per month) | C43: =C48 -> 10 | D43: =D48 -> 50 | E43: =E48 -> 150 | F43: Documented: IMPACTLENS PRICING MODEL.xlsx › D66:H66. Linked to section 4.
B44: Add-ons, overage, trial and other discounts are proposed in section 6 (not in the source docs).
B46: 4 · UNIT ECONOMICS (cost floor if the tier's allowances are fully used)
B47: Line | C47: Starter | D47: Pro | E47: Enterprise | F47: Source / note
B48: Cloudinary credits included / mo | C48: 10 | D48: 50 | E48: 150 | F48: Documented: IMPACTLENS PRICING MODEL.xlsx › D18:F18.
B49: AI vision analyses included / mo | C49: 100 | D49: 1000 | E49: 5000 | F49: Documented: IMPACTLENS PRICING MODEL.xlsx › D20:F20.
B50: Reports + semantic searches cost (₹ / mo) | C50: 3 | D50: 180 | E50: 650 | F50: Documented: IMPACTLENS PRICING MODEL.xlsx › D22:F22. A typed number: the workbook gives no derivation.
B51: ₹ per Cloudinary credit | C51: 34 | F51: Documented assumption: IMPACTLENS PRICING MODEL.xlsx › D12 ('~₹34 per credit'). CONTRADICTED by Cloudinary's published price: see the alternative block below and Open Items O-01.
B52: ₹ per AI vision analysis | C52: 0.9 | F52: Assumption stated as such in the source: IMPACTLENS PRICING MODEL.xlsx › D13 ('AI cost basis (assumption)'). Not measured.
B53: Cloudinary cost (₹ / mo) | C53: =C48*$C$51 -> 340 | D53: =D48*$C$51 -> 1700 | E53: =E48*$C$51 -> 5100 | F53: Calculated: credits × ₹ per credit.
B54: AI analysis cost (₹ / mo) | C54: =C49*$C$52 -> 90 | D54: =D49*$C$52 -> 900 | E54: =E49*$C$52 -> 4500 | F54: Calculated: analyses × ₹ per analysis.
B55: Total estimated COGS (₹ / mo) | C55: =C53+C54+C50 -> 433 | D55: =D53+D54+D50 -> 2780 | E55: =E53+E54+E50 -> 10250 | F55: Calculated. Matches the source workbook's row 23. Excludes hosting, support, payment fees and tax (Open Items O-09).
B56: Gross profit (₹ / mo) | C56: =C15-C55 -> 2566 | D56: =D15-D55 -> 5219 | E56: =E15-E55 -> 9749 | F56: Calculated: annual-plan price − COGS.
B57: Gross margin (as modelled) | C57: =C56/C15 -> 0.85561854 | D57: =D56/D15 -> 0.65245656 | E57: =E56/E15 -> 0.48747437 | F57: Calculated. Matches the source workbook's row 25.
B58: Alternative basis: Cloudinary's published price
B59: Cloudinary Plus, annual billing ($ / month) | C59: 89 | F59: Documented: docs/competitors.csv › cloudinary row (https://cloudinary.com/pricing, verified 2026-09-29). Same $89 the source workbook cites.
B60: Credits included on Plus (per month) | C60: 225 | F60: Documented: same source ('225 credits').
B61: Implied ₹ per credit | C61: =$C$59/$C$60*$C$8 -> 38.001022 | F61: Calculated at the workbook's own FX rate. Higher than the ₹34 used in the model.
B62: COGS at the published credit price (₹ / mo) | C62: =C48*$C$61+C54+C50 -> 473.01022 | D62: =D48*$C$61+D54+D50 -> 2980.0511 | E62: =E48*$C$61+E54+E50 -> 10850.153 | F62: Calculated: same as the model with credits priced at the implied rate.
B63: Gross margin at the published credit price | C63: =(C15-C62)/C15 -> 0.84227735 | D63: =(D15-D62)/D15 -> 0.62744704 | E63: =(E15-E62)/E15 -> 0.45746521 | F63: Calculated. A sensitivity, not a replacement for the model's assumption.
B64: Frames sent per video | C64: 6 | F64: Documented: docs/IMPACTLENS PRICING MODEL.xlsx › 'Cost Inputs'!C29 (code cap in videoFramesAsParts).
B65: COGS if every analysis is a video (₹ / mo) | C65: =C62 -> 473.01022 | D65: =D48*$C$61+D54*$C$64+D50 -> 7480.0511 | E65: =E48*$C$61+E54*$C$64+E50 -> 33350.153 | F65: Calculated upper bound (Starter has no video, so unchanged). The allowance does not say whether a video is one unit or up to six (Open Items O-06).
B66: Gross margin, all-video upper bound | C66: =(C15-C65)/C15 -> 0.84227735 | D66: =(D15-D65)/D15 -> 0.064876721 | E66: =(E15-E65)/E15 -> -0.66759105 | F66: Calculated. Negative means the tier loses money if its analysis allowance is used on video.
B68: 5 · PHASE 2 PRICE TRAJECTORY (documented; not yet in effect)
B69: Line | C69: Starter | D69: Pro | E69: Enterprise | F69: Source / note
B70: Phase 1 price (₹ / month) | C70: =C15 -> 2999 | D70: =D15 -> 7999 | E70: =E15 -> 19999 | F70: Linked from section 2.
B71: Phase 2 price: low (₹ / month) | C71: 4000 | D71: 12000 | E71: 29000 | F71: Documented: IMPACTLENS PRICING MODEL.xlsx › D74:D76.
B72: Phase 2 price: high (₹ / month) | C72: 5000 | D72: 15000 | E72: 39000 | F72: Documented: IMPACTLENS PRICING MODEL.xlsx › D74:D76.
B73: Uplift vs Phase 1: low | C73: =C71/C70-1 -> 0.33377793 | D73: =D71/D70-1 -> 0.50018752 | E73: =E71/E70-1 -> 0.4500725 | F73: Calculated.
B74: Uplift vs Phase 1: high | C74: =C72/C70-1 -> 0.66722241 | D74: =D72/D70-1 -> 0.8752344 | E74: =E72/E70-1 -> 0.9500975 | F74: Calculated.
B75: What is added (documented) | C75: Public API + 500 analyses / mo | D75: SSO + audit trail + unlimited semantic search | E75: Multi-funder dashboards + verifier sign-off + 99.9% SLA | F75: Documented: IMPACTLENS PRICING MODEL.xlsx › D74:D76. Rationale (D77): verification workflow, SSO/RBAC, immutable audit log, public API, BYOC storage, 99.9% uptime SLA.
B76: Trigger for Phase 2 pricing | C76: 50 paying orgs + public API pilot + funder-verification pilots closed | F76: Documented: IMPACTLENS PRICING MODEL.xlsx › D72. Whether existing customers are grandfathered is not documented (Open Items O-12).
B78: 6 · DISCOUNTS, ADD-ONS, UPSELL AND PRICING ASSUMPTIONS
B79: Item | C79: Status | F79: Detail / source
B80: Annual-billing discount | C80: Documented | F80: 17% (annual plan is the base price; the monthly plan is the marked-up price).
B81: Other discounts (nonprofit, volume, multi-year, launch) | C81: Assumption | F81: ="2-year prepay: a further "&TEXT('Planning Inputs'!$D$70,"0%")&" off the annual price. No nonprofit or launch discount (every customer is an impact org; the base price already targets them)." -> 2-year prepay: a further 5% off the annual price. No nonprofit or launch discount (every customer is an impact org; the base price already targets them).
B82: Add-ons (extra credits, analyses, seats, storage) | C82: Assumption | F82: ="Extra AI analysis ₹"&'Planning Inputs'!$D$67&" each; extra Cloudinary credit ₹"&'Planning Inputs'!$D$68&" each; extra seat ₹"&'Planning Inputs'!$D$69&" / month (Starter, Pro). Priced at "&'Planning Inputs'!$D$66&"× unit cost." -> Extra AI analysis ₹3 each; extra Cloudinary credit ₹114 each; extra seat ₹500 / month (Starter, Pro). Priced at 3× unit cost.
B83: Overage pricing | C83: Assumption | F83: Soft limit: past 100% of an allowance, extra use bills at the add-on prices above; after 3 months over, prompt an upgrade. Must be built before limits are enforced (memo U3).
B84: Free tier / trial | C84: Assumption | F84: ="14-day opt-in trial with Pro features, capped at "&'Planning Inputs'!$D$28&" analyses and "&'Planning Inputs'!$D$29&" credits: ₹"&TEXT('Planning Inputs'!$D$30,"#,##0")&" per trial org, ₹"&TEXT('Planning Inputs'!$D$30/'Planning Inputs'!$D$23,"#,##0")&" of trial cost per paying org." -> 14-day opt-in trial with Pro features, capped at 25 analyses and 2 credits: ₹99 per trial org, ₹980 of trial cost per paying org.
B85: Upsell path: Starter → Pro | C85: Documented | F85: Feature fences: video analysis, semantic search, report variants, campaign copy, share links, leaderboard and CSV export start at Pro; limits rise (assets 250 → 5,000, comparisons 5 → 100).
B86: Upsell path: Pro → Enterprise | C86: Documented | F86: Scheduled reports + email delivery, unlimited orgs / seats / assets / comparisons, 150 reports / mo, dedicated support.
B87: Expansion at Phase 2 | C87: Documented | F87: Prices rise 33%–67% (section 5) when SSO, RBAC, audit log, public API and verifier workflow ship.
B88: Bring-your-own-key (BYOK) pricing lever | C88: Hypothesis | F88: Proposed, not decided: docs/COMPETITIVE-LANDSCAPE.md › U11. ImpactDraft offers 25% off for customers using their own key (verified 2026-09-29).
B89: Price validation with customers | C89: Assumption | F89: No customer conversation recorded yet. Plan: 10 buyer interviews with Van Westendorp price questions before Phase 2; until then the documented Phase 1 prices stand.

Sheet Revenue Model
B2: REVENUE MODEL
B3: Sections A and B are exact arithmetic on documented prices. Section C is a 12-month scenario driven entirely by 'Planning Inputs' (labelled assumptions and benchmarks, not documented facts). Sections D and E derive CAC, retention, costs outside COGS and market size from the same inputs.
B5: A · PER-CUSTOMER ECONOMICS (annual-plan price, cost floor at full allowance use)
B6: Per organisation | C6: Starter | D6: Pro | E6: Enterprise
B7: MRR per customer (₹) | C7: =Pricing!C15 -> 2999 | D7: =Pricing!D15 -> 7999 | E7: =Pricing!E15 -> 19999
B8: ARR per customer (₹) | C8: =C7*12 -> 35988 | D8: =D7*12 -> 95988 | E8: =E7*12 -> 239988
B9: COGS per customer (₹ / mo) | C9: =Pricing!C55 -> 433 | D9: =Pricing!D55 -> 2780 | E9: =Pricing!E55 -> 10250
B10: Gross profit per customer (₹ / mo) | C10: =C7-C9 -> 2566 | D10: =D7-D9 -> 5219 | E10: =E7-E9 -> 9749
B11: Gross margin | C11: =C10/C7 -> 0.85561854 | D11: =D10/D7 -> 0.65245656 | E11: =E10/E7 -> 0.48747437
B12: MRR per customer if on the monthly plan (₹) | C12: =Pricing!C17 -> 3613 | D12: =Pricing!D17 -> 9637 | E12: =Pricing!E17 -> 24095
B13: MRR per customer (USD, indicative) | C13: =Pricing!C16 -> 31 | D13: =Pricing!D16 -> 83 | E13: =Pricing!E16 -> 208
B14: COGS assumes every allowance is fully used (a cost floor for a heavy user), so margins here are conservative for light users and ignore hosting, support, payment fees, tax and the uncosted features (Open Items O-09).
B16: B · SCALE ARITHMETIC (N organisations on ONE tier; illustrative multiplication, not a forecast)
B17: N organisations | C17: 1 | D17: 10 | E17: 50 | F17: N = 50 is the documented Phase 2 trigger (IMPACTLENS PRICING MODEL.xlsx › D72). 1 and 10 are scale points, not targets.
B18: MRR (₹) if all N are on… | C18: N = 1 | D18: N = 10 | E18: N = 50
B19: Starter | C19: =C$17*INDEX($C$7:$E$7,1) -> 2999 | D19: =D$17*INDEX($C$7:$E$7,1) -> 29990 | E19: =E$17*INDEX($C$7:$E$7,1) -> 149950
B20: Pro | C20: =C$17*INDEX($C$7:$E$7,2) -> 7999 | D20: =D$17*INDEX($C$7:$E$7,2) -> 79990 | E20: =E$17*INDEX($C$7:$E$7,2) -> 399950
B21: Enterprise | C21: =C$17*INDEX($C$7:$E$7,3) -> 19999 | D21: =D$17*INDEX($C$7:$E$7,3) -> 199990 | E21: =E$17*INDEX($C$7:$E$7,3) -> 999950
B22: ARR (₹) if all N are on… | C22: N = 1 | D22: N = 10 | E22: N = 50
B23: Starter | C23: =C$17*INDEX($C$8:$E$8,1) -> 35988 | D23: =D$17*INDEX($C$8:$E$8,1) -> 359880 | E23: =E$17*INDEX($C$8:$E$8,1) -> 1799400
B24: Pro | C24: =C$17*INDEX($C$8:$E$8,2) -> 95988 | D24: =D$17*INDEX($C$8:$E$8,2) -> 959880 | E24: =E$17*INDEX($C$8:$E$8,2) -> 4799400
B25: Enterprise | C25: =C$17*INDEX($C$8:$E$8,3) -> 239988 | D25: =D$17*INDEX($C$8:$E$8,3) -> 2399880 | E25: =E$17*INDEX($C$8:$E$8,3) -> 11999400
B26: Gross profit / month (₹) if all N are on… | C26: N = 1 | D26: N = 10 | E26: N = 50
B27: Starter | C27: =C$17*INDEX($C$10:$E$10,1) -> 2566 | D27: =D$17*INDEX($C$10:$E$10,1) -> 25660 | E27: =E$17*INDEX($C$10:$E$10,1) -> 128300
B28: Pro | C28: =C$17*INDEX($C$10:$E$10,2) -> 5219 | D28: =D$17*INDEX($C$10:$E$10,2) -> 52190 | E28: =E$17*INDEX($C$10:$E$10,2) -> 260950
B29: Enterprise | C29: =C$17*INDEX($C$10:$E$10,3) -> 9749 | D29: =D$17*INDEX($C$10:$E$10,3) -> 97490 | E29: =E$17*INDEX($C$10:$E$10,3) -> 487450
B31: C · SCENARIO (12 months; annual-plan prices; inputs linked from 'Planning Inputs')
B32: =IF(SUM(D35:O37)+SUM(D38:O39)=0,"NO SCENARIO INPUTS: outputs below show '-'.","Scenario active: driven by Planning Inputs (sign-ups, funnel, mix, churn, upgrades). A planning scenario, not a documented forecast.") -> Scenario active: driven by Planning Inputs (sign-ups, funnel, mix, churn, upgrades). A planning scenario, not a documented forecast.
B33: Line | C33: Monthly churn | D33: M1 | E33: M2 | F33: M3 | G33: M4 | H33: M5 | I33: M6 | J33: M7 | K33: M8 | L33: M9 | M33: M10 | N33: M11 | O33: M12
B34: INPUTS
B35: New customers: Starter | D35: ='Planning Inputs'!$D$14*(1+'Planning Inputs'!$D$15)^0*'Planning Inputs'!$D$23*'Planning Inputs'!$D$34 -> 1.809864 | E35: ='Planning Inputs'!$D$14*(1+'Planning Inputs'!$D$15)^1*'Planning Inputs'!$D$23*'Planning Inputs'!$D$34 -> 1.9546531 | F35: ='Planning Inputs'!$D$14*(1+'Planning Inputs'!$D$15)^2*'Planning Inputs'!$D$23*'Planning Inputs'!$D$34 -> 2.1110254 | G35: ='Planning Inputs'!$D$14*(1+'Planning Inputs'!$D$15)^3*'Planning Inputs'!$D$23*'Planning Inputs'!$D$34 -> 2.2799074 | H35: ='Planning Inputs'!$D$14*(1+'Planning Inputs'!$D$15)^4*'Planning Inputs'!$D$23*'Planning Inputs'!$D$34 -> 2.4623 | I35: ='Planning Inputs'!$D$14*(1+'Planning Inputs'!$D$15)^5*'Planning Inputs'!$D$23*'Planning Inputs'!$D$34 -> 2.659284 | J35: ='Planning Inputs'!$D$14*(1+'Planning Inputs'!$D$15)^6*'Planning Inputs'!$D$23*'Planning Inputs'!$D$34 -> 2.8720267 | K35: ='Planning Inputs'!$D$14*(1+'Planning Inputs'!$D$15)^7*'Planning Inputs'!$D$23*'Planning Inputs'!$D$34 -> 3.1017888 | L35: ='Planning Inputs'!$D$14*(1+'Planning Inputs'!$D$15)^8*'Planning Inputs'!$D$23*'Planning Inputs'!$D$34 -> 3.349932 | M35: ='Planning Inputs'!$D$14*(1+'Planning Inputs'!$D$15)^9*'Planning Inputs'!$D$23*'Planning Inputs'!$D$34 -> 3.6179265 | N35: ='Planning Inputs'!$D$14*(1+'Planning Inputs'!$D$15)^10*'Planning Inputs'!$D$23*'Planning Inputs'!$D$34 -> 3.9073606 | O35: ='Planning Inputs'!$D$14*(1+'Planning Inputs'!$D$15)^11*'Planning Inputs'!$D$23*'Planning Inputs'!$D$34 -> 4.2199495
B36: New customers: Pro | D36: ='Planning Inputs'!$D$14*(1+'Planning Inputs'!$D$15)^0*'Planning Inputs'!$D$23*'Planning Inputs'!$D$35 -> 0.904932 | E36: ='Planning Inputs'!$D$14*(1+'Planning Inputs'!$D$15)^1*'Planning Inputs'!$D$23*'Planning Inputs'!$D$35 -> 0.97732656 | F36: ='Planning Inputs'!$D$14*(1+'Planning Inputs'!$D$15)^2*'Planning Inputs'!$D$23*'Planning Inputs'!$D$35 -> 1.0555127 | G36: ='Planning Inputs'!$D$14*(1+'Planning Inputs'!$D$15)^3*'Planning Inputs'!$D$23*'Planning Inputs'!$D$35 -> 1.1399537 | H36: ='Planning Inputs'!$D$14*(1+'Planning Inputs'!$D$15)^4*'Planning Inputs'!$D$23*'Planning Inputs'!$D$35 -> 1.23115 | I36: ='Planning Inputs'!$D$14*(1+'Planning Inputs'!$D$15)^5*'Planning Inputs'!$D$23*'Planning Inputs'!$D$35 -> 1.329642 | J36: ='Planning Inputs'!$D$14*(1+'Planning Inputs'!$D$15)^6*'Planning Inputs'!$D$23*'Planning Inputs'!$D$35 -> 1.4360134 | K36: ='Planning Inputs'!$D$14*(1+'Planning Inputs'!$D$15)^7*'Planning Inputs'!$D$23*'Planning Inputs'!$D$35 -> 1.5508944 | L36: ='Planning Inputs'!$D$14*(1+'Planning Inputs'!$D$15)^8*'Planning Inputs'!$D$23*'Planning Inputs'!$D$35 -> 1.674966 | M36: ='Planning Inputs'!$D$14*(1+'Planning Inputs'!$D$15)^9*'Planning Inputs'!$D$23*'Planning Inputs'!$D$35 -> 1.8089633 | N36: ='Planning Inputs'!$D$14*(1+'Planning Inputs'!$D$15)^10*'Planning Inputs'!$D$23*'Planning Inputs'!$D$35 -> 1.9536803 | O36: ='Planning Inputs'!$D$14*(1+'Planning Inputs'!$D$15)^11*'Planning Inputs'!$D$23*'Planning Inputs'!$D$35 -> 2.1099747
B37: New customers: Enterprise | D37: ='Planning Inputs'!$D$14*(1+'Planning Inputs'!$D$15)^0*'Planning Inputs'!$D$23*'Planning Inputs'!$D$36 -> 0.301644 | E37: ='Planning Inputs'!$D$14*(1+'Planning Inputs'!$D$15)^1*'Planning Inputs'!$D$23*'Planning Inputs'!$D$36 -> 0.32577552 | F37: ='Planning Inputs'!$D$14*(1+'Planning Inputs'!$D$15)^2*'Planning Inputs'!$D$23*'Planning Inputs'!$D$36 -> 0.35183756 | G37: ='Planning Inputs'!$D$14*(1+'Planning Inputs'!$D$15)^3*'Planning Inputs'!$D$23*'Planning Inputs'!$D$36 -> 0.37998457 | H37: ='Planning Inputs'!$D$14*(1+'Planning Inputs'!$D$15)^4*'Planning Inputs'!$D$23*'Planning Inputs'!$D$36 -> 0.41038333 | I37: ='Planning Inputs'!$D$14*(1+'Planning Inputs'!$D$15)^5*'Planning Inputs'!$D$23*'Planning Inputs'!$D$36 -> 0.443214 | J37: ='Planning Inputs'!$D$14*(1+'Planning Inputs'!$D$15)^6*'Planning Inputs'!$D$23*'Planning Inputs'!$D$36 -> 0.47867112 | K37: ='Planning Inputs'!$D$14*(1+'Planning Inputs'!$D$15)^7*'Planning Inputs'!$D$23*'Planning Inputs'!$D$36 -> 0.51696481 | L37: ='Planning Inputs'!$D$14*(1+'Planning Inputs'!$D$15)^8*'Planning Inputs'!$D$23*'Planning Inputs'!$D$36 -> 0.55832199 | M37: ='Planning Inputs'!$D$14*(1+'Planning Inputs'!$D$15)^9*'Planning Inputs'!$D$23*'Planning Inputs'!$D$36 -> 0.60298775 | N37: ='Planning Inputs'!$D$14*(1+'Planning Inputs'!$D$15)^10*'Planning Inputs'!$D$23*'Planning Inputs'!$D$36 -> 0.65122677 | O37: ='Planning Inputs'!$D$14*(1+'Planning Inputs'!$D$15)^11*'Planning Inputs'!$D$23*'Planning Inputs'!$D$36 -> 0.70332491
B38: Upgrades: Starter → Pro (customers) | D38: 0 | E38: =D45*'Planning Inputs'!$D$40 -> 0.03619728 | F38: =E45*'Planning Inputs'!$D$40 -> 0.073480478 | G38: =F45*'Planning Inputs'!$D$40 -> 0.11202696 | H38: =G45*'Planning Inputs'!$D$40 -> 0.15202376 | I38: =H45*'Planning Inputs'!$D$40 -> 0.19366857 | J38: =I45*'Planning Inputs'!$D$40 -> 0.23717082 | K38: =J45*'Planning Inputs'!$D$40 -> 0.28275282 | L38: =K45*'Planning Inputs'!$D$40 -> 0.33065095 | ... O38: =N45*'Planning Inputs'!$D$40 -> 0.49084595
B39: Upgrades: Pro → Enterprise (customers) | D39: 0 | E39: =D46*'Planning Inputs'!$D$41 -> 0.00904932 | F39: =E46*'Planning Inputs'!$D$41 -> 0.018958325 | G39: =F46*'Planning Inputs'!$D$41 -> 0.029774299 | H39: =G46*'Planning Inputs'!$D$41 -> 0.041549748 | I39: =H46*'Planning Inputs'!$D$41 -> 0.054342742 | J39: =I46*'Planning Inputs'!$D$41 -> 0.068217279 | K39: =J46*'Planning Inputs'!$D$41 -> 0.083243689 | L39: =K46*'Planning Inputs'!$D$41 -> 0.099499069 | ... O39: =N46*'Planning Inputs'!$D$41 -> 0.15652182
B40: Monthly churn by tier | D40: Linked from Planning Inputs section 4 (benchmark ranges in the note).
B41: Monthly churn: Starter | C41: ='Planning Inputs'!$D$37 -> 0.03 | D41: Planning Inputs: SMB SaaS benchmark 3–7% a month.
B42: Monthly churn: Pro | C42: ='Planning Inputs'!$D$38 -> 0.015 | D42: Planning Inputs: Mid-market benchmark 0.5–1.5% a month.
B43: Monthly churn: Enterprise | C43: ='Planning Inputs'!$D$39 -> 0.007 | D43: Planning Inputs: Enterprise benchmark < 0.5–0.7% a month.
B44: OUTPUTS
B45: Customers (end): Starter | D45: =N(D35)-N(D38) -> 1.809864 | E45: =D45*(1-$C$41)+N(E35)-N(E38) -> 3.6740239 | F45: =E45*(1-$C$41)+N(F35)-N(F38) -> 5.6013481 | G45: =F45*(1-$C$41)+N(G35)-N(G38) -> 7.6011881 | H45: =G45*(1-$C$41)+N(H35)-N(H38) -> 9.6834287 | I45: =H45*(1-$C$41)+N(I35)-N(I38) -> 11.858541 | J45: =I45*(1-$C$41)+N(J35)-N(J38) -> 14.137641 | K45: =J45*(1-$C$41)+N(K35)-N(K38) -> 16.532548 | L45: =K45*(1-$C$41)+N(L35)-N(L38) -> 19.055852 | ... O45: =N45*(1-$C$41)+N(O35)-N(O38) -> 27.535132
B46: Customers (end): Pro | D46: =N(D36)+N(D38)-N(D39) -> 0.904932 | E46: =D46*(1-$C$42)+N(E36)+N(E38)-N(E39) -> 1.8958325 | F46: =E46*(1-$C$42)+N(F36)+N(F38)-N(F39) -> 2.9774299 | G46: =F46*(1-$C$42)+N(G36)+N(G38)-N(G39) -> 4.1549748 | H46: =G46*(1-$C$42)+N(H36)+N(H38)-N(H39) -> 5.4342742 | I46: =H46*(1-$C$42)+N(I36)+N(I38)-N(I39) -> 6.8217279 | J46: =I46*(1-$C$42)+N(J36)+N(J38)-N(J39) -> 8.3243689 | K46: =J46*(1-$C$42)+N(K36)+N(K38)-N(K39) -> 9.9499069 | L46: =K46*(1-$C$42)+N(L36)+N(L38)-N(L39) -> 11.706776 | ... O46: =N46*(1-$C$42)+N(O36)+N(O38)-N(O39) -> 17.861699
B47: Customers (end): Enterprise | D47: =N(D37)+N(D39) -> 0.301644 | E47: =D47*(1-$C$43)+N(E37)+N(E39) -> 0.63435733 | F47: =E47*(1-$C$43)+N(F37)+N(F39) -> 1.0007127 | G47: =F47*(1-$C$43)+N(G37)+N(G39) -> 1.4034666 | H47: =G47*(1-$C$43)+N(H37)+N(H39) -> 1.8455754 | I47: =H47*(1-$C$43)+N(I37)+N(I39) -> 2.3302131 | J47: =I47*(1-$C$43)+N(J37)+N(J39) -> 2.86079 | K47: =J47*(1-$C$43)+N(K37)+N(K39) -> 3.440973 | L47: =K47*(1-$C$43)+N(L37)+N(L39) -> 4.0747072 | ... O47: =N47*(1-$C$43)+N(O37)+N(O39) -> 6.3413505
B48: Customers (end): total | D48: =SUM(D45:D47) -> 3.01644 | E48: =SUM(E45:E47) -> 6.2042138 | F48: =SUM(F45:F47) -> 9.5794907 | G48: =SUM(G45:G47) -> 13.159629 | H48: =SUM(H45:H47) -> 16.963278 | I48: =SUM(I45:I47) -> 21.010482 | J48: =SUM(J45:J47) -> 25.3228 | K48: =SUM(K45:K47) -> 29.923428 | ... O48: =SUM(O45:O47) -> 51.738181
B49: MRR: Starter (₹) | D49: =D45*C$7 -> 5427.7821 | E49: =E45*C$7 -> 11018.398 | F49: =F45*C$7 -> 16798.443 | G49: =G45*C$7 -> 22795.963 | H49: =H45*C$7 -> 29040.603 | I49: =I45*C$7 -> 35563.765 | J49: =J45*C$7 -> 42398.785 | K49: =K45*C$7 -> 49581.11 | L49: =L45*C$7 -> 57148.501 | M49: =M45*C$7 -> 65141.237 | N49: =N45*C$7 -> 73602.35 | O49: =O45*C$7 -> 82577.861
B50: MRR: Pro (₹) | D50: =D46*D$7 -> 7238.5511 | E50: =E46*D$7 -> 15164.764 | F50: =F46*D$7 -> 23816.462 | G50: =G46*D$7 -> 33235.643 | H50: =H46*D$7 -> 43468.759 | I50: =I46*D$7 -> 54567.002 | J50: =J46*D$7 -> 66586.627 | K50: =K46*D$7 -> 79589.305 | L50: =L46*D$7 -> 93642.503 | M50: =M46*D$7 -> 108819.89 | N50: =N46*D$7 -> 125201.81 | O50: =O46*D$7 -> 142875.73
B51: MRR: Enterprise (₹) | D51: =D47*E$7 -> 6032.5784 | E51: =E47*E$7 -> 12686.512 | F51: =F47*E$7 -> 20013.254 | G51: =G47*E$7 -> 28067.928 | H51: =H47*E$7 -> 36909.663 | I51: =I47*E$7 -> 46601.932 | J51: =J47*E$7 -> 57212.94 | K51: =K47*E$7 -> 68816.019 | L51: =L47*E$7 -> 81490.07 | M51: =M47*E$7 -> 95320.03 | N51: =N47*E$7 -> 110397.38 | O51: =O47*E$7 -> 126820.67
B52: MRR: total (₹) | D52: =SUM(D49:D51) -> 18698.912 | E52: =SUM(E49:E51) -> 38869.675 | F52: =SUM(F49:F51) -> 60628.158 | G52: =SUM(G49:G51) -> 84099.535 | H52: =SUM(H49:H51) -> 109419.02 | I52: =SUM(I49:I51) -> 136732.7 | J52: =SUM(J49:J51) -> 166198.35 | K52: =SUM(K49:K51) -> 197986.43 | ... O52: =SUM(O49:O51) -> 352274.26
B53: ARR run-rate (₹) = MRR × 12 | D53: =D52*12 -> 224386.94 | E53: =E52*12 -> 466436.09 | F53: =F52*12 -> 727537.9 | G53: =G52*12 -> 1009194.4 | H53: =H52*12 -> 1313028.3 | I53: =I52*12 -> 1640792.4 | J53: =J52*12 -> 1994380.2 | K53: =K52*12 -> 2375837.2 | ... O53: =O52*12 -> 4227291.1
B54: Expansion MRR from upgrades (₹) | D54: =N(D38)*($D$7-$C$7)+N(D39)*($E$7-$D$7) -> 0 | E54: =N(E38)*($D$7-$C$7)+N(E39)*($E$7-$D$7) -> 289.57824 | F54: =N(F38)*($D$7-$C$7)+N(F39)*($E$7-$D$7) -> 594.9023 | G54: =N(G38)*($D$7-$C$7)+N(G39)*($E$7-$D$7) -> 917.4264 | H54: =N(H38)*($D$7-$C$7)+N(H39)*($E$7-$D$7) -> 1258.7158 | I54: =N(I38)*($D$7-$C$7)+N(I39)*($E$7-$D$7) -> 1620.4558 | J54: =N(J38)*($D$7-$C$7)+N(J39)*($E$7-$D$7) -> 2004.4615 | K54: =N(K38)*($D$7-$C$7)+N(K39)*($E$7-$D$7) -> 2412.6884 | ... O54: =N(O38)*($D$7-$C$7)+N(O39)*($E$7-$D$7) -> 4332.4916
B55: Gross profit (₹ / month) | D55: =D45*$C$10+D46*$D$10+D47*$E$10 -> 12307.678 | E55: =E45*$C$10+E46*$D$10+E47*$E$10 -> 25506.245 | F55: =F45*$C$10+F46*$D$10+F47*$E$10 -> 39668.214 | G55: =G45*$C$10+G46*$D$10+G47*$E$10 -> 54871.858 | H55: =H45*$C$10+H46*$D$10+H47*$E$10 -> 71201.67 | I55: =I45*$C$10+I46*$D$10+I47*$E$10 -> 88748.862 | J55: =J45*$C$10+J46*$D$10+J47*$E$10 -> 107611.91 | K55: =K45*$C$10+K46*$D$10+K47*$E$10 -> 127897.13 | ... O55: =O45*$C$10+O46*$D$10+O47*$E$10 -> 225697.18
B56: Blended gross margin | D56: =IF(D52=0,0,D55/D52) -> 0.65820294 | E56: =IF(E52=0,0,E55/E52) -> 0.65619909 | F56: =IF(F52=0,0,F55/F52) -> 0.65428697 | G56: =IF(G52=0,0,G55/G52) -> 0.65246327 | H56: =IF(H52=0,0,H55/H52) -> 0.65072477 | I56: =IF(I52=0,0,I55/I52) -> 0.64906831 | J56: =IF(J52=0,0,J55/J52) -> 0.64749084 | K56: =IF(K52=0,0,K55/K52) -> 0.64598934 | ... O56: =IF(O52=0,0,O55/O52) -> 0.64068599
B58: Still not modelled: sales-cycle length, seasonality, Phase 2 repricing of existing customers (Open Items O-12), the monthly-plan share of customers. GST is collected on top of price, so it is not a cost here.
B60: D · UNIT ECONOMICS, CAC AND RETENTION (per organisation)
B61: Per organisation | C61: Starter | D61: Pro | E61: Enterprise
B62: Monthly logo churn | C62: ='Planning Inputs'!$D$37 -> 0.03 | D62: ='Planning Inputs'!$D$38 -> 0.015 | E62: ='Planning Inputs'!$D$39 -> 0.007
B63: Annual logo churn | C63: =1-(1-C62)^12 -> 0.30615764 | D63: =1-(1-D62)^12 -> 0.16586803 | E63: =1-(1-E62)^12 -> 0.080840285
B64: Expected lifetime (months) | C64: =1/C62 -> 33.333333 | D64: =1/D62 -> 66.666667 | E64: =1/E62 -> 142.85714
B65: Lifetime gross profit, LTV (₹) | C65: =C10*C64 -> 85533.333 | D65: =D10*D64 -> 347933.33 | E65: =E10*E64 -> 1392714.3
B66: Target CAC payback (months) | C66: ='Planning Inputs'!$D$45 -> 12 | D66: ='Planning Inputs'!$D$45 -> 12 | E66: ='Planning Inputs'!$D$46 -> 18
B67: Max CAC at that payback (₹) | C67: =C10*C66 -> 30792 | D67: =D10*D66 -> 62628 | E67: =E10*E66 -> 175482
B68: LTV : CAC | C68: =C65/C67 -> 2.7777778 | D68: =D65/D67 -> 5.5555556 | E68: =E65/E67 -> 7.9365079
B69: Payment-gateway fee incl. GST on fee (₹ / mo) | C69: =C7*'Planning Inputs'!$D$51*(1+'Planning Inputs'!$D$50) -> 70.7764 | D69: =D7*'Planning Inputs'!$D$51*(1+'Planning Inputs'!$D$50) -> 188.7764 | E69: =E7*'Planning Inputs'!$D$51*(1+'Planning Inputs'!$D$50) -> 471.9764
B70: Support cost (₹ / mo) | C70: ='Planning Inputs'!$D$52 -> 150 | D70: ='Planning Inputs'!$D$53 -> 500 | E70: ='Planning Inputs'!$D$54 -> 4000
B71: Contribution after fees and support (₹ / mo) | C71: =C10-C69-C70 -> 2345.2236 | D71: =D10-D69-D70 -> 4530.2236 | E71: =E10-E69-E70 -> 5277.0236
B72: Contribution margin | C72: =C71/C7 -> 0.78200187 | D72: =D71/D7 -> 0.56634874 | E72: =E71/E7 -> 0.26386437
B74: Scenario KPIs by month
B75: Line | D75: M1 | E75: M2 | F75: M3 | G75: M4 | H75: M5 | I75: M6 | J75: M7 | K75: M8 | L75: M9 | M75: M10 | N75: M11 | O75: M12
B76: Churned MRR (₹) | D76: =0 -> 0 | E76: =D45*$C$41*$C$7+D46*$C$42*$D$7+D47*$C$43*$E$7 -> 313.63978 | F76: =E45*$C$41*$C$7+E46*$C$42*$D$7+E47*$C$43*$E$7 -> 646.82899 | G76: =F45*$C$41*$C$7+F46*$C$42*$D$7+F47*$C$43*$E$7 -> 1001.293 | H76: =G45*$C$41*$C$7+G46*$C$42*$D$7+G47*$C$43*$E$7 -> 1378.889 | I76: =H45*$C$41*$C$7+H46*$C$42*$D$7+H47*$C$43*$E$7 -> 1781.6171 | J76: =I45*$C$41*$C$7+I46*$C$42*$D$7+I47*$C$43*$E$7 -> 2211.6315 | K76: =J45*$C$41*$C$7+J46*$C$42*$D$7+J47*$C$43*$E$7 -> 2671.2535 | L76: =K45*$C$41*$C$7+K46*$C$42*$D$7+K47*$C$43*$E$7 -> 3162.985 | ... O76: =N45*$C$41*$C$7+N46*$C$42*$D$7+N47*$C$43*$E$7 -> 4858.8792
B77: Net revenue retention (month on month) | D77: ="n/a" -> n/a | E77: =IF(D52=0,"n/a",(D52-E76+E54)/D52) -> 0.99871321 | F77: =IF(E52=0,"n/a",(E52-F76+F54)/E52) -> 0.99866408 | G77: =IF(F52=0,"n/a",(F52-G76+G54)/F52) -> 0.99861671 | H77: =IF(G52=0,"n/a",(G52-H76+H54)/G52) -> 0.99857106 | I77: =IF(H52=0,"n/a",(H52-I76+I54)/H52) -> 0.99852712 | J77: =IF(I52=0,"n/a",(I52-J76+J54)/I52) -> 0.99848485 | K77: =IF(J52=0,"n/a",(J52-K76+K54)/J52) -> 0.99844424 | L77: =IF(K52=0,"n/a",(K52-L76+L54)/K52) -> 0.99840524 | ... O77: =IF(N52=0,"n/a",(N52-O76+O54)/N52) -> 0.99829759
B78: New paying orgs | D78: =D35+D36+D37 -> 3.01644 | E78: =E35+E36+E37 -> 3.2577552 | F78: =F35+F36+F37 -> 3.5183756 | G78: =G35+G36+G37 -> 3.7998457 | H78: =H35+H36+H37 -> 4.1038333 | I78: =I35+I36+I37 -> 4.43214 | J78: =J35+J36+J37 -> 4.7867112 | K78: =K35+K36+K37 -> 5.1696481 | ... O78: =O35+O36+O37 -> 7.0332491
B79: Acquisition spend at max CAC (₹) | D79: =D35*$C$67+D36*$D$67+D37*$E$67 -> 165336.51 | E79: =E35*$C$67+E36*$D$67+E37*$E$67 -> 178563.43 | F79: =F35*$C$67+F36*$D$67+F37*$E$67 -> 192848.5 | G79: =G35*$C$67+G36*$D$67+G37*$E$67 -> 208276.38 | H79: =H35*$C$67+H36*$D$67+H37*$E$67 -> 224938.49 | I79: =I35*$C$67+I36*$D$67+I37*$E$67 -> 242933.57 | J79: =J35*$C$67+J36*$D$67+J37*$E$67 -> 262368.26 | K79: =K35*$C$67+K36*$D$67+K37*$E$67 -> 283357.72 | ... O79: =O35*$C$67+O36*$D$67+O37*$E$67 -> 385505.05
B80: Hosting (₹) | D80: ='Planning Inputs'!$D$55 -> 8000 | E80: ='Planning Inputs'!$D$55 -> 8000 | F80: ='Planning Inputs'!$D$55 -> 8000 | G80: ='Planning Inputs'!$D$55 -> 8000 | H80: ='Planning Inputs'!$D$55 -> 8000 | I80: ='Planning Inputs'!$D$55 -> 8000 | J80: ='Planning Inputs'!$D$55 -> 8000 | K80: ='Planning Inputs'!$D$55 -> 8000 | ... O80: ='Planning Inputs'!$D$55 -> 8000
B81: Gateway fees + support (₹) | D81: =D45*($C$69+$C$70)+D46*($D$69+$D$70)+D47*($E$69+$E$70) -> 2371.8159 | E81: =E45*($C$69+$C$70)+E46*($D$69+$D$70)+E47*($E$69+$E$70) -> 4953.7735 | F81: =F45*($C$69+$C$70)+F46*($D$69+$D$70)+F47*($E$69+$E$70) -> 7762.5926 | G81: =G45*($C$69+$C$70)+G46*($D$69+$D$70)+G47*($E$69+$E$70) -> 10816.281 | H81: =H45*($C$69+$C$70)+H46*($D$69+$D$70)+H47*($E$69+$E$70) -> 14134.242 | I81: =I45*($C$69+$C$70)+I46*($D$69+$D$70)+I47*($E$69+$E$70) -> 17737.389 | J81: =J45*($C$69+$C$70)+J46*($D$69+$D$70)+J47*($E$69+$E$70) -> 21648.272 | K81: =K45*($C$69+$C$70)+K46*($D$69+$D$70)+K47*($E$69+$E$70) -> 25891.207 | ... O81: =O45*($C$69+$C$70)+O46*($D$69+$D$70)+O47*($E$69+$E$70) -> 46740.194
B82: Operating contribution (₹) | D82: =D55-D79-D80-D81 -> -163400.64 | E82: =E55-E79-E80-E81 -> -166010.95 | F82: =F55-F79-F80-F81 -> -168942.88 | G82: =G55-G79-G80-G81 -> -172220.8 | H82: =H55-H79-H80-H81 -> -175871.06 | I82: =I55-I79-I80-I81 -> -179922.1 | J82: =J55-J79-J80-J81 -> -184404.62 | K82: =K55-K79-K80-K81 -> -189351.8 | ... O82: =O55-O79-O80-O81 -> -214548.06
B83: Cumulative operating contribution (₹) | D83: =D82 -> -163400.64 | E83: =D83+E82 -> -329411.6 | F83: =E83+F82 -> -498354.48 | G83: =F83+G82 -> -670575.28 | H83: =G83+H82 -> -846446.34 | I83: =H83+I82 -> -1026368.4 | J83: =I83+J82 -> -1210773.1 | K83: =J83+K82 -> -1400124.9 | L83: =K83+L82 -> -1594924.3 | ... O83: =N83+O82 -> -2217612.8
B85: Scenario summary
B86: Paying orgs at M12 | C86: =O48 -> 51.738181
B87: ARR run-rate at M12 (₹) | C87: =O53 -> 4227291.1
B88: 12-month net revenue retention | C88: =PRODUCT(E77:O77)^(12/11) -> 0.98206596
B89: Blended CAC over 12 months (₹) | C89: =SUM(D79:O79)/SUM(D78:O78) -> 54811.8
B90: Sign-up → paid conversion | C90: ='Planning Inputs'!$D$23 -> 0.100548
B91: Month the 50-org Phase 2 trigger is reached | C91: =IF(MAX(D48:O48)>=50,COUNTIF(D48:O48,"<50")+1,"after M12") -> 12
B92: Date of that month | C92: =IF(ISNUMBER(C91),EDATE('Planning Inputs'!$D$9,C91-1),"after "&TEXT(EDATE('Planning Inputs'!$D$9,11),"mmm yyyy")) -> 46631
B93: Break-even month (operating contribution ≥ 0) | C93: =IF(MAX(D82:O82)>=0,COUNTIF(D82:O82,"<0")+1,"after M12") -> after M12 | D93: Spend is the CAC ceiling, not a budget: at max CAC the scenario does not break even in year 1.
B95: E · MARKET SIZE (India, bottom-up; ₹ crore = ₹ 10,000,000)
B96: Level | C96: Orgs | D96: ₹ crore / yr | E96: Basis
B97: Blended annual price per org, ARPA (₹) | D97: ='Planning Inputs'!$D$34*C8+'Planning Inputs'!$D$35*D8+'Planning Inputs'!$D$36*E8 -> 74388 | E97: New-customer mix × annual-plan ARR.
B98: TAM: FCRA NGOs + CSR-spending companies | C98: ='Planning Inputs'!$D$59+'Planning Inputs'!$D$60 -> 41654 | D98: =C98*$D$97/10^7 -> 309.85578 | E98: Every org in India with a formal duty to evidence funded work.
B99: SAM: reachable with a media-evidence product | C99: =C98*'Planning Inputs'!$D$61 -> 12496.2 | D99: =C99*$D$97/10^7 -> 92.956733 | E99: TAM × Planning Inputs share.
B100: SOM: won within 3 years | C100: =C99*'Planning Inputs'!$D$62 -> 249.924 | D100: =C100*$D$97/10^7 -> 1.8591347 | E100: SAM × Planning Inputs share.

Sheet Competitive Positioning
B2: COMPETITIVE POSITIONING
B3: Source: docs/competitors.csv and docs/COMPETITIVE-LANDSCAPE.md (verified 2026-09-29); the seven rows previously unverified were re-researched on 2026-09-30 through a search tool (Medium confidence unless the pricing page itself was read). 'Not stated on the page read' is NOT evidence of absence. Quote-only prices are shown in text, not in the USD column.
B5: ImpactLens reference (linked from Pricing) | E5: Pro tier price (USD / month) | F5: =Pricing!D16 -> 83
B7: Competitor | C7: Role | D7: Target customer | E7: Pricing (public, as documented) | F7: USD / mo (lowest paid, monthly equiv.) | G7: × ImpactLens Pro price | H7: Product positioning | I7: Key strengths (stated on source) | J7: Relevant gaps (evidence-limited) | K7: Our differentiation | L7: Confidence | M7: Last verified | N7: Source URL
B8: Fulcrum | C8: capture-verify | D8: Field teams (segments not stated on pricing page) | E8: Professional $43/user/mo; Elite $55/user/mo; Enterprise custom; min 5 users | F8: 215 | G8: =F8/$F$5 -> 2.5903614 | H8: Mobile field data capture with photos, video, audio, GPS | I8: capture with geotag / timestamp; offline capture | J8: Not stated on the page read: photo/video AI (not proof of absence). | K8: ImpactLens does not capture media; it analyses and reports on it. This competitor is stronger on proof of capture. Possible import partner (hypothesis, memo U12). | L8: High | M8: 2026-09-29 | N8: https://www.fulcrumapp.com/pricing
B9: CommCare (Dimagi) | C9: capture-verify | D9: NGOs, governments, social enterprises, donors and foundations, researchers | E9: Standard $100/mo; Pro $500/mo; Advanced $1,000/mo; Enterprise $4,000+/mo | F9: 100 | G9: =F9/$F$5 -> 1.2048193 | H9: Mobile data collection and case management | I9: None stated on the page read | J9: Not stated on the page read: photo/video AI (not proof of absence). | K9: ImpactLens does not capture media; it analyses and reports on it. This competitor is stronger on proof of capture. Possible import partner (hypothesis, memo U12). | L9: High | M9: 2026-09-29 | N9: https://commcare.dimagi.com/pricing/
B10: Sealr (UNDP Digital X) | C10: capture-verify | D10: UN and government agencies in humanitarian response; field staff, partners, affected communities | E10: not stated | H10: Timestamped, geolocated, AI-verified and blockchain-secured photo/video capture on a map dashboard | I10: capture with geotag / timestamp | J10: Page (© 2022) does not explain what the 'AI-verified' step does; product status unknown. | K10: ImpactLens does not capture media; it analyses and reports on it. This competitor is stronger on proof of capture. Possible import partner (hypothesis, memo U12). | L10: Medium | M10: 2026-09-29 | N10: https://digitalx.undp.org/catalogs/sealr.html
B11: Tella | C11: capture-verify | D11: Activists, journalists, human-rights defenders | E11: Free forever (vendor statement) | F11: Free | H11: Encrypted offline-first photo/video/audio capture | I11: offline capture | J11: Not stated on the page read: photo/video AI (not proof of absence). | K11: ImpactLens does not capture media; it analyses and reports on it. This competitor is stronger on proof of capture. Possible import partner (hypothesis, memo U12). | L11: High | M11: 2026-09-29 | N11: https://tella.app
B12: BNZ Impact | C12: capture-verify | D12: Corporates and CSR teams, NGOs, foundations, restoration developers, sustainability teams | E12: No pricing on page | H12: Baseline capture, geo-tagged photos, satellite verification, exportable evidence packs | I12: capture with geotag / timestamp | J12: Not stated on the page read: photo/video AI (not proof of absence). | K12: ImpactLens does not capture media; it analyses and reports on it. This competitor is stronger on proof of capture. Possible import partner (hypothesis, memo U12). | L12: High | M12: 2026-09-29 | N12: https://bnzgreen.io/impact
B13: KoboToolbox | C13: capture-verify | D13: Humanitarian and development field data collection | E13: Community free (5,000 submissions / mo); Professional $159/mo ($129 billed annually); Teams $289/mo ($249 annually) | F13: 129 | G13: =F13/$F$5 -> 1.5542169 | H13: Survey/form data collection | I13: Offline form capture with GPS, photo, audio and video questions; free Community plan | J13: Media is stored as form attachments; no photo / video AI or report drafting stated (not proof of absence). | K13: Import partner, not a rival: ImpactLens analyses the photos Kobo collects (memo U12). Chauka already imports from Kobo, which shows the connector pattern works. | L13: Medium | M13: 2026-09-30 | N13: https://www.kobotoolbox.org/pricing/
B14: Sopact | C14: report-ai | D14: Nonprofits, foundations, social enterprises, mission-driven organisations | E14: Power $299/mo (2 users, 500 AI analyses/yr, 1,500 responses); Growth $799/mo (3 users, 2,000 analyses/yr); Enterprise custom; setup from $200/hr, 10-hour minimum | F14: 299 | G14: =F14/$F$5 -> 3.6024096 | H14: AI analysis of forms, files and feedback into funder-aligned reports | I14: reports / evidence packs | J14: Not stated on the page read: photo/video AI (not proof of absence). Home page describes forms, files and feedback; no photo analysis stated. | K14: ImpactLens grounds reports in analysed media evidence and lists the source assets; this competitor's evidence base is text or forms, as stated on its page. Hypothesis: buyers will pay more for media-grounded evidence. | L14: High | M14: 2026-09-29 | N14: https://sopact.com
B15: ReportsAI | C15: report-ai | D15: Grassroots NGOs to multinational enterprises | E15: No pricing on home page; /pricing returned 404 | H15: AI reporting against SDGs, IRIS+, GRI, ESG with offline multilingual data capture | I15: SDG / IRIS+ / GRI alignment; offline capture | J15: Not stated on the page read: photo/video AI (not proof of absence). | K15: ImpactLens grounds reports in analysed media evidence and lists the source assets; this competitor's evidence base is text or forms, as stated on its page. Hypothesis: buyers will pay more for media-grounded evidence. | L15: High | M15: 2026-09-29 | N15: https://reports-ai.app
B16: ImpactDraft | C16: report-ai | D16: Small local NGOs to international organisations | E16: Free demo (3 reports); Basic $9/mo (30 reports); Pro $19/mo (100 reports); Enterprise $49/mo (unlimited) | F16: 9 | G16: =F16/$F$5 -> 0.10843373 | H16: Donor report generator (7 report types, 5 languages) | I16: reports / evidence packs | J16: Not stated on the page read: photo/video AI (not proof of absence). Text only; no media evidence stated. | K16: ImpactLens grounds reports in analysed media evidence and lists the source assets; this competitor's evidence base is text or forms, as stated on its page. Hypothesis: buyers will pay more for media-grounded evidence. | L16: High | M16: 2026-09-29 | N16: https://impactdraft.org
B17: engage by Kindsight | C17: report-ai | D17: Nonprofits: education, healthcare, arts, community foundations, faith-based | E17: No pricing on page | H17: AI donor communications and grant-proposal drafting | I17: AI donor copy | J17: Not stated on the page read: photo/video AI (not proof of absence). | K17: ImpactLens grounds reports in analysed media evidence and lists the source assets; this competitor's evidence base is text or forms, as stated on its page. Hypothesis: buyers will pay more for media-grounded evidence. | L17: High | M17: 2026-09-29 | N17: https://kindsight.io/engage
B18: DevResults | C18: me-suite | D18: Global development organisations managing funded programs | E18: Setup $33,800 (<=$5M program) to $103,400 (<=$100M); annual $28,000 (<=$5M), $49,000 (<=$25M), $70,000 (<=$50M); training $5,000-$15,000; unlimited users and storage | F18: 2333 | G18: =F18/$F$5 -> 28.108434 | H18: Monitoring and evaluation software | I18: None stated on the page read | J18: Not stated on the page read: photo/video AI (not proof of absence). | K18: Different job (program-level M&E) and a different budget. Far cheaper than ImpactLens Enterprise (see ratio) but ImpactLens offers no indicator / logframe management. Hypothesis: competes for the same reporting budget. | L18: High | M18: 2026-09-29 | N18: https://www.devresults.com/pricing
B19: Chauka | C19: me-suite | D19: Development organisations that plan with logical frameworks | E19: Open source; no public price found | H19: Open-source M&E / logframe (prior doc) | I19: Logframe design, indicator targets and actuals, budget lines, KoboToolbox and Google Sheets import, quarterly donor reports | J19: No photo / video evidence handling stated (not proof of absence). | K19: Different job (programme-level M&E / logframes) and a different budget; ImpactLens offers no indicator management. Complementary: its analysed media could feed their indicators. | L19: Medium | M19: 2026-09-30 | N19: https://chauka.org
B20: MONIC | C20: me-suite | D20: Researchers, nonprofits, government agencies | E20: Open source (AGPL-3.0); no public price | H20: Open-source M&E (prior doc) | I20: KPI tracking, theory-of-change builder, logframes, surveys with optional ChatGPT analysis, document repository | J20: No photo / video AI stated (not proof of absence). | K20: Different job (programme-level M&E / logframes) and a different budget; ImpactLens offers no indicator management. Complementary: its analysed media could feed their indicators. | L20: Medium | M20: 2026-09-30 | N20: https://www.monic.tech/
B21: MEInsight | C21: me-suite | D21: unknown | E21: Not public | H21: Open-source M&E / logframe | I21: None stated on the page read | J21: Last commit 2023-11-08: dormant. | K21: Different job (program-level M&E) and a different budget. Far cheaper than ImpactLens Enterprise (see ratio) but ImpactLens offers no indicator / logframe management. Hypothesis: competes for the same reporting budget. | L21: Medium | M21: 2026-09-29 | N21: https://github.com/edc-it/MEInsight
B22: Uwazi (HURIDOCS) | C22: me-suite | D22: Human-rights documentation | E22: Not public | H22: Evidence document collections with search | I22: None stated on the page read | J22: — | K22: Different job (program-level M&E) and a different budget. Far cheaper than ImpactLens Enterprise (see ratio) but ImpactLens offers no indicator / logframe management. Hypothesis: competes for the same reporting budget. | L22: Medium | M22: 2026-09-29 | N22: https://github.com/HURIDOCS/uwazi
B23: Amp Impact (Vera Solutions) | C23: me-suite | D23: Salesforce-based nonprofits (prior doc) | E23: From $7,000 / year; nonprofit discounts; custom quotes (Capterra listing) | F23: 583 | G23: =F23/$F$5 -> 7.0240964 | H23: Salesforce-packaged impact measurement (prior doc) | I23: Native Salesforce app: grant and portfolio management, indicator tracking, work planning; 17,000+ users in 150+ countries | J23: Requires Salesforce; no media AI stated (not proof of absence). | K23: Different job and budget (Salesforce M&E, ≈ 7× ImpactLens Pro). ImpactLens is lighter and media-first; no CRM needed. | L23: Medium | M23: 2026-09-30 | N23: https://www.verasolutions.org/ampimpact/
B24: Watershed | C24: esg-suite | D24: Enterprise ESG and carbon disclosure | E24: Custom quote only; third-party estimates $50k–$250k+ / year, median ≈ $70k (Vendr) | H24: Carbon/ESG reporting (prior doc) | I24: Enterprise carbon accounting (Scope 1–3) and disclosure reporting | J24: Carbon and financial data, not field media. | K24: Different buyer and job (corporate carbon disclosure). Overlaps only with S3 CSR teams' reporting budget; candidate to drop from the landscape. | L24: Medium | M24: 2026-09-30 | N24: https://watershed.com
B25: Persefoni | C25: esg-suite | D25: Enterprise ESG and carbon disclosure | E25: Pro: free (single user); Advanced: custom quote | F25: Free | H25: Carbon/ESG reporting (prior doc) | I25: Scope 1–3 (all 15 categories), report builder for CSRD / ISSB / CDP, AI copilot; SSO and SOC 2 on Advanced | J25: Carbon data, not field media. | K25: Different buyer and job (corporate carbon disclosure). Overlaps only with S3 CSR teams' reporting budget; candidate to drop from the landscape. | L25: High | M25: 2026-09-30 | N25: https://www.persefoni.com/pricing
B26: Sweep | C26: esg-suite | D26: Enterprise ESG and carbon disclosure | E26: No public price; Starter and Pro tiers by quote (third-party listing) | H26: Carbon/ESG reporting (prior doc) | I26: Carbon management, supplier data collection, CSRD reporting | J26: Carbon data, not field media. | K26: Different buyer and job (corporate carbon disclosure). Overlaps only with S3 CSR teams' reporting budget; candidate to drop from the landscape. | L26: Medium | M26: 2026-09-30 | N26: https://www.sweep.net
B27: Ecodrive ImpactIQ | C27: marketplace | D27: Nonprofits selling verified impact to corporate partners; corporate buyers | E27: Projects from $0.45 per unit; Enterprise from a $50k annual impact commitment | H27: Donor portals and dashboards showing timestamps, geo-coordinates and photos of each partner's contribution | I27: capture with geotag / timestamp; SDG / IRIS+ / GRI alignment | J27: Not stated on the page read: photo/video AI, baseline / before-after (not proof of absence). Page describes a corporate-donation marketplace, not a media library. | K27: Different model: sells verified impact units to corporate buyers. Not comparable on price. | L27: High | M27: 2026-09-29 | N27: https://www.ecodrive.community/impactiq
B28: Cloudinary | C28: platform-vendor | D28: Developers and brands managing image/video | E28: Free 25 credits; Plus $99/mo ($89/mo annual) 225 credits incl. auto-tagging; Advanced $249/mo ($224 annual) 600 credits; Enterprise custom; 1 credit = 1,000 transformations or 1 GB storage or 1 GB image bandwidth (2 GB video) | F28: 89 | G28: =F28/$F$5 -> 1.0722892 | H28: Media storage, transformation, CDN, DAM, AI auto-tagging | I28: photo/video AI | J28: — | K28: Cloudinary is ImpactLens's storage and CDN supplier and also offers its own auto-tagging. ImpactLens differentiates on workflow (evidence chain → cited report → schedule), not on tagging. | L28: High | M28: 2026-09-29 | N28: https://cloudinary.com/documentation/cloudinary_ai_content_analysis_addon
B29: TextIt / RapidPro | C29: channel | D29: Organisations messaging contacts by SMS and WhatsApp | E29: $25/mo for the first 1,000 messaged contacts, then $0.01 per additional contact; special pricing for registered non-profits | F29: 25 | G29: =F29/$F$5 -> 0.30120482 | H29: Messaging flows and campaigns | I29: None stated on the page read | J29: — | K29: A possible delivery channel (SMS / WhatsApp), not a rival. | L29: High | M29: 2026-09-29 | N29: https://textit.com/pricing
B30: MIRL Aftermath | C30: reference-oss | D30: Heritage professionals, conservators, human-rights researchers | E30: Free | F30: Free | H30: Before/after photo condition dossiers for courts and UNESCO submissions | I30: baseline / before-after; reports / evidence packs | J30: — | K30: Design reference; not sold to buyers. | L30: High | M30: 2026-09-29 | N30: https://github.com/mirl-ucsb/mirl-aftermath
B31: impact-vision | C31: reference-oss | D31: VC and impact investment funds | E31: Free | F31: Free | H31: AI agent mapping reported impact to IRIS+, SDGs and 20+ ESG frameworks | I31: SDG / IRIS+ / GRI alignment | J31: — | K31: Design reference; not sold to buyers. | L31: High | M31: 2026-09-29 | N31: https://github.com/joejoe168168/impact-vision
B32: impact-reporter-ai | C32: reference-oss | D32: n/a (repository removed) | E32: n/a | H32: n/a: repository returns HTTP 404 | I32: n/a | J32: Repository returns HTTP 404. | K32: None needed: dead link. Remove from the landscape. | L32: Dead | M32: 2026-09-29 | N32: https://github.com/maree217/impact-reporter-ai
B34: PRICE SUMMARY (calculated from the rows above)
B35: Competitors with a numeric price | E35: =COUNT(F8:F32) -> 9
B36: Lowest (USD / month) | E36: =MIN(F8:F32) -> 9
B37: Median (USD / month) | E37: =MEDIAN(F8:F32) -> 129
B38: Highest (USD / month) | E38: =MAX(F8:F32) -> 2333
B39: Priced below ImpactLens Starter | E39: =COUNTIF(F8:F32,"<"&Pricing!C16) -> 2
B40: Priced above ImpactLens Enterprise | E40: =COUNTIF(F8:F32,">"&Pricing!E16) -> 4
B41: Prices are each vendor's lowest paid public plan, converted to a monthly equivalent; they cover different products (text report writers, form-based M&E, field capture, M&E suites), so this is context, not a like-for-like comparison. Detail: docs/IMPACTLENS PRICING MODEL.xlsx › 'Price Benchmark'.

Sheet Planning Inputs
B2: PLANNING INPUTS
B3: Every number the source documents did not give lives here. Blue = typed assumption or public figure · black = formula · yellow = key assumption the owner should confirm. Change a blue cell and every sheet updates. Prepared 2026-09-30. Benchmarks are third-party figures read through a search tool: re-read before external use.
B6: 1 · GEOGRAPHY, DATES AND SALES MOTION
B7: ID | C7: Input | D7: Value | E7: Unit | F7: Basis / source | G7: Type
B8: P01 | C8: Launch geography and billing currency | D8: India first: INR billing with GST invoices and Razorpay checkout. English-speaking international NGOs billed in USD (indicative prices on Pricing) once a USD checkout exists. | E8: text | F8: Prices are INR-primary (IMPACTLENS PRICING MODEL.xlsx › D7). India holds the reachable, reporting-obliged base counted in section 6. Resolves Open Items O-04 as a planning assumption. | G8: Assumption
B9: P02 | C9: Planning start (month M1) | D9: 46296 | E9: date | F9: First month after this workbook was prepared (2026-09-30). | G9: Assumption
B10: P03 | C10: Sales motion | D10: Self-serve trial and web checkout for Starter and Pro; founder-led sales for Enterprise, CSR and funder buyers. No resellers in year 1. | E10: text | F10: Follows the support model (Email / Email + Chat / Dedicated + SLA; IMPACTLENS PRICING MODEL.xlsx › row 69). | G10: Assumption
B12: 2 · FUNNEL (organisations; each rate is conversion from the previous stage)
B13: ID | C13: Input | D13: Value | E13: Unit | F13: Basis / source | G13: Type
B14: P04 | C14: New sign-ups in M1 | D14: 30 | E14: orgs / month | F14: Sized so the documented Phase 2 trigger (50 paying orgs) is reached inside 12 months at the rates below. | G14: Assumption
B15: P05 | C15: Sign-up growth | D15: 0.08 | E15: per month | F15: Early-stage content + referral growth; no measured traffic exists yet. | G15: Assumption
B16: P06 | C16: Site visit → sign-up | D16: 0.025 | E16: rate | F16: B2B SaaS visit-to-sign-up typically 1–3% (saashero.net, orbix.studio 2026 conversion benchmarks). | G16: Benchmark
B17: P07 | C17: Sign-up → first upload | D17: 0.7 | E17: rate | F17: Upload is the first action after creating an org (PRD F1–F2). | G17: Assumption
B18: P08 | C18: First upload → first analysis | D18: 0.95 | E18: rate | F18: Analysis runs automatically on upload (PRD F3); the loss is failed or unsupported files. | G18: Assumption
B19: P09 | C19: First analysis → value moment | D19: 0.7 | E19: rate | F19: Value moment = search, filter, compare or project view used (PRD F4–F7). | G19: Assumption
B20: P10 | C20: Value moment → first report / campaign | D20: 0.6 | E20: rate | F20: Activation = ≥ 1 analysed asset and ≥ 1 generated report (proposed definition). | G20: Assumption
B21: P11 | C21: Report → share or schedule | D21: 0.6 | E21: rate | F21: Share link or scheduled delivery (PRD F10–F11). | G21: Assumption
B22: P12 | C22: Share → paid | D22: 0.6 | E22: rate | F22: End of the free trial below. | G22: Assumption
B23: P13 | C23: Sign-up → paid (calculated) | D23: ='Planning Inputs'!$D$17*'Planning Inputs'!$D$18*'Planning Inputs'!$D$19*'Planning Inputs'!$D$20*'Planning Inputs'!$D$21*'Planning Inputs'!$D$22 -> 0.100548 | E23: rate | F23: Product of the stage rates. Check: opt-in (no card) trial-to-paid benchmark 8–22%, median 14% (growthspreeofficial.com 2026 trial benchmarks). | G23: Calculated
B25: 3 · FREE TRIAL
B26: ID | C26: Input | D26: Value | E26: Unit | F26: Basis / source | G26: Type
B27: P14 | C27: Trial length | D27: 14 | E27: days | F27: Common B2B SaaS opt-in trial length. | G27: Assumption
B28: P15 | C28: AI analyses allowed in the trial | D28: 25 | E28: analyses | F28: Enough for one project's before/after set. | G28: Assumption
B29: P16 | C29: Cloudinary credits allowed in the trial | D29: 2 | E29: credits | F29: Covers ~25 uploads and previews. | G29: Assumption
B30: P17 | C30: Cost per trial org (calculated) | D30: ='Planning Inputs'!$D$28*Pricing!$C$52+'Planning Inputs'!$D$29*Pricing!$C$61 -> 98.502044 | E30: ₹ per trial | F30: Analyses × ₹ per analysis + credits × ₹ per credit at Cloudinary's published price (Pricing C52, C61). | G30: Calculated
B32: 4 · NEW PAYING MIX, CHURN AND UPGRADES
B33: ID | C33: Input | D33: Value | E33: Unit | F33: Basis / source | G33: Type
B34: P18 | C34: New paying orgs choosing Starter | D34: 0.6 | E34: share | F34: Most likely S5 and small S1 teams (ICP tier fit). | G34: Assumption
B35: P19 | C35: New paying orgs choosing Pro | D35: 0.3 | E35: share | F35: S1 and S2 teams needing search and campaign copy. | G35: Assumption
B36: P20 | C36: New paying orgs choosing Enterprise | D36: =1-'Planning Inputs'!$D$34-'Planning Inputs'!$D$35 -> 0.1 | E36: share | F36: Remainder, so the mix always sums to 100%. | G36: Calculated
B37: P21 | C37: Monthly logo churn: Starter | D37: 0.03 | E37: per month | F37: SMB SaaS 3–7% a month, SMB-heavy average ≈ 4% (meltingspot.io, churnfree.com 2026 benchmarks). Annual plans pull it to the low end. | G37: Benchmark
B38: P22 | C38: Monthly logo churn: Pro | D38: 0.015 | E38: per month | F38: Mid-market 0.5–1.5% a month (same sources). | G38: Benchmark
B39: P23 | C39: Monthly logo churn: Enterprise | D39: 0.007 | E39: per month | F39: Enterprise < 0.5% best in class; ≈ 0.7% average (same sources). | G39: Benchmark
B40: P24 | C40: Upgrades Starter → Pro | D40: 0.02 | E40: of Starter base / month | F40: Driven by the Pro feature fences (video, search, share links, campaign copy). | G40: Assumption
B41: P25 | C41: Upgrades Pro → Enterprise | D41: 0.01 | E41: of Pro base / month | F41: Driven by scheduled reports, unlimited seats and dedicated support. | G41: Assumption
B43: 5 · ACQUISITION COST
B44: ID | C44: Input | D44: Value | E44: Unit | F44: Basis / source | G44: Type
B45: P26 | C45: Target CAC payback: Starter and Pro | D45: 12 | E45: months | F45: Common SaaS guardrail: recover CAC from gross profit within 12 months. | G45: Benchmark
B46: P27 | C46: Target CAC payback: Enterprise | D46: 18 | E46: months | F46: Sales-led deals tolerate a longer payback. | G46: Benchmark
B48: 6 · COSTS OUTSIDE COGS AND TAX
B49: ID | C49: Input | D49: Value | E49: Unit | F49: Basis / source | G49: Type
B50: P28 | C50: GST on SaaS (India) | D50: 0.18 | E50: of price | F50: 18% GST on online information / SaaS services. Charged on top of the price and remitted, so it is not a cost if prices are quoted ex-GST. | G50: Public rate
B51: P29 | C51: Payment-gateway fee | D51: 0.02 | E51: of charge | F51: Razorpay standard plan: 2% domestic (3% international cards) + 18% GST on the fee (razorpay.com/blog/razorpay-payment-gateway-pricing-explained). | G51: Public rate
B52: P30 | C52: Support cost: Starter | D52: 150 | E52: ₹ / org / month | F52: Email only; ≈ 15 min a month of support time. | G52: Assumption
B53: P31 | C53: Support cost: Pro | D53: 500 | E53: ₹ / org / month | F53: Email + chat. | G53: Assumption
B54: P32 | C54: Support cost: Enterprise | D54: 4000 | E54: ₹ / org / month | F54: Dedicated + SLA: ≈ 10% of one support hire per account. | G54: Assumption
B55: P33 | C55: Hosting (fixed) | D55: 8000 | E55: ₹ / month | F55: One app VM + database backups + email; deployment target is undecided (PRD §7). | G55: Assumption
B57: 7 · MARKET SIZE INPUTS (India)
B58: ID | C58: Input | D58: Value | E58: Unit | F58: Basis / source | G58: Type
B59: P34 | C59: Active FCRA-registered NGOs | D59: 14466 | E59: orgs | F59: Receive foreign funds, so they owe donors evidence. MHA data reported by ThePrint / Millennium Post, 2025. | G59: Public figure
B60: P35 | C60: Companies spending CSR (FY 2023-24) | D60: 27188 | E60: orgs | F60: National CSR Portal: 27,188 companies spent ₹34,908.75 crore (The CSR Journal, 2025). | G60: Public figure
B61: P36 | C61: Share reachable with a media-evidence product | D61: 0.3 | E61: of TAM orgs | F61: Orgs that run field programmes with photo or video evidence and buy software online. | G61: Assumption
B62: P37 | C62: Share of SAM won in 3 years | D62: 0.02 | E62: of SAM orgs | F62: Typical early-stage obtainable share. | G62: Assumption
B64: 8 · ADD-ONS, OVERAGE AND DISCOUNTS
B65: ID | C65: Input | D65: Value | E65: Unit | F65: Basis / source | G65: Type
B66: P38 | C66: Add-on price as a multiple of unit cost | D66: 3 | E66: × | F66: Keeps add-on gross margin ≈ 67%, near the Pro tier's modelled 65%. | G66: Assumption
B67: P39 | C67: Extra AI analysis (calculated) | D67: =ROUND(Pricing!$C$52*'Planning Inputs'!$D$66,0) -> 3 | E67: ₹ each | F67: ₹ per analysis × markup, rounded. | G67: Calculated
B68: P40 | C68: Extra Cloudinary credit (calculated) | D68: =ROUND(Pricing!$C$61*'Planning Inputs'!$D$66,0) -> 114 | E68: ₹ each | F68: Published-price credit × markup, rounded. | G68: Calculated
B69: P41 | C69: Extra seat (Starter, Pro) | D69: 500 | E69: ₹ / seat / month | F69: Priced so 3 extra Starter seats (₹1,500) stay below the ₹5,000 step to Pro. | G69: Assumption
B70: P42 | C70: 2-year prepay discount (on top of annual) | D70: 0.05 | E70: off annual price | F70: No nonprofit or launch discount: every customer is an impact org and the base price already targets them. | G70: Assumption
B72: 9 · SEGMENT ATTRACTIVENESS SCORING (1 = weak, 5 = strong)
B73: ID | C73: Segment | D73: Pain | E73: Ability to pay | F73: Reachability | G73: Product fit today | H73: Score | I73: Rank
C74: Weight | D74: 0.3 | E74: 0.25 | F74: 0.2 | G74: 0.25 | H74: =SUM(D74:G74) -> 1
B75: S1 | C75: Program teams at NGOs | D75: 5 | E75: 3 | F75: 4 | G75: 5 | H75: =SUMPRODUCT(D75:G75,$D$74:$G$74) -> 4.3 | I75: =RANK(H75,$H$75:$H$80) -> 1
B76: S2 | C76: Comms and fundraising teams | D76: 4 | E76: 2 | F76: 4 | G76: 5 | H76: =SUMPRODUCT(D76:G76,$D$74:$G$74) -> 3.75 | I76: =RANK(H76,$H$75:$H$80) -> 3
B77: S3 | C77: Corporate CSR teams | D77: 4 | E77: 5 | F77: 3 | G77: 2 | H77: =SUMPRODUCT(D77:G77,$D$74:$G$74) -> 3.55 | I77: =RANK(H77,$H$75:$H$80) -> 4
B78: S4 | C78: Governments | D78: 3 | E78: 4 | F78: 1 | G78: 1 | H78: =SUMPRODUCT(D78:G78,$D$74:$G$74) -> 2.35 | I78: =RANK(H78,$H$75:$H$80) -> 6
B79: S5 | C79: Small / mid NGOs, no M&E staff | D79: 5 | E79: 2 | F79: 3 | G79: 5 | H79: =SUMPRODUCT(D79:G79,$D$74:$G$74) -> 3.85 | I79: =RANK(H79,$H$75:$H$80) -> 2
B80: S6 | C80: Funder-verification orgs (Phase 2) | D80: 4 | E80: 5 | F80: 2 | G80: 1 | H80: =SUMPRODUCT(D80:G80,$D$74:$G$74) -> 3.1 | I80: =RANK(H80,$H$75:$H$80) -> 5
B81: Scores are the preparer's judgement from the ICP evidence (e.g. S3/S4/S6 fit is low because the product has no GPS, content hash or verifier workflow yet). Replace them after customer interviews.

Sheet Assumptions & Sources
B2: ASSUMPTIONS & SOURCES
B3: Every input or claim used in this workbook. Values in green are live links to the sheet where they are used, so this register cannot drift from the model. Note: docs/COMPETITIVE-LANDSCAPE.md and docs/competitors.csv were written during a product audit on 2026-09-29; their content is analysis and recommendation (Hypothesis), not a management decision. docs/IMPACTLENS PRICING MODEL.xlsx (pricing) is the only original planning document.
B5: ID | C5: Area | D5: Item | E5: Value | F5: Unit | G5: Source document | H5: Section / location | I5: Type | J5: Confidence / status | K5: Note
B6: A01 | C6: Pricing | D6: Starter price, annual plan | E6: =Pricing!C15 -> 2999 | F6: ₹ / month | G6: IMPACTLENS PRICING MODEL.xlsx | H6: ImpactLens Pricing › D31 | I6: Documented | J6: High
B7: A02 | C7: Pricing | D7: Pro price, annual plan | E7: =Pricing!D15 -> 7999 | F7: ₹ / month | G7: IMPACTLENS PRICING MODEL.xlsx | H7: ImpactLens Pricing › E31 | I7: Documented | J7: High
B8: A03 | C8: Pricing | D8: Enterprise price, annual plan | E8: =Pricing!E15 -> 19999 | F8: ₹ / month | G8: IMPACTLENS PRICING MODEL.xlsx | H8: ImpactLens Pricing › F31 | I8: Documented | J8: High
B9: A04 | C9: Pricing | D9: Annual billing discount | E9: =Pricing!$C$7 -> 0.17 | F9: % | G9: IMPACTLENS PRICING MODEL.xlsx | H9: ImpactLens Pricing › D6 | I9: Documented | J9: High
B10: A05 | C10: Pricing | D10: USD → INR rate | E10: =Pricing!$C$8 -> 96.07 | F10: ₹ per $ | G10: IMPACTLENS PRICING MODEL.xlsx | H10: ImpactLens Pricing › D8 | I10: Documented | J10: Medium | K10: Marked editable; date and source of the rate not documented.
B11: A06 | C11: Pricing | D11: Monthly-plan price rule: annual ÷ (1 − discount) | E11: formula | G11: IMPACTLENS PRICING MODEL.xlsx | H11: ImpactLens Pricing › D11 | I11: Documented | J11: High
B12: A07 | C12: Pricing | D12: Monthly-plan price, Starter / Pro / Enterprise | E12: =TEXT(Pricing!C17,"#,##0")&" / "&TEXT(Pricing!D17,"#,##0")&" / "&TEXT(Pricing!E17,"#,##0") -> 3,613 / 9,637 / 24,095 | F12: ₹ / month | G12: IMPACTLENS PRICING MODEL.xlsx | H12: Derived from D11 | I12: Calculated | J12: High
B13: A08 | C13: Pricing | D13: Prices are per organisation per month | E13: per org | G13: IMPACTLENS PRICING MODEL.xlsx | H13: ImpactLens Pricing › A16 ('COGS per org / month') | I13: Documented | J13: Medium | K13: Unit inferred from the COGS heading.
B14: A09 | C14: Pricing | D14: Tier-to-segment maturity (Low / Mid / High) | E14: Low / Mid / High | G14: IMPACTLENS PRICING MODEL.xlsx | H14: ImpactLens Pricing › D30:F30 | I14: Documented | J14: Low | K14: Criteria undefined.
B15: A10 | C15: Pricing | D15: Cloudinary credits included per tier | E15: =Pricing!C48&" / "&Pricing!D48&" / "&Pricing!E48 -> 10 / 50 / 150 | F15: credits / mo | G15: IMPACTLENS PRICING MODEL.xlsx | H15: ImpactLens Pricing › D18:F18 | I15: Documented | J15: High
B16: A11 | C16: Pricing | D16: AI vision analyses included per tier | E16: =Pricing!C49&" / "&Pricing!D49&" / "&Pricing!E49 -> 100 / 1000 / 5000 | F16: per month | G16: IMPACTLENS PRICING MODEL.xlsx | H16: ImpactLens Pricing › D20:F20 | I16: Documented | J16: High
B17: A12 | C17: Pricing | D17: Reports + semantic-search cost per tier | E17: =Pricing!C50&" / "&Pricing!D50&" / "&Pricing!E50 -> 3 / 180 / 650 | F17: ₹ / month | G17: IMPACTLENS PRICING MODEL.xlsx | H17: ImpactLens Pricing › D22:F22 | I17: Documented | J17: Low | K17: Typed number; no derivation given.
B18: A13 | C18: Unit economics | D18: ₹ per Cloudinary credit | E18: =Pricing!$C$51 -> 34 | F18: ₹ | G18: IMPACTLENS PRICING MODEL.xlsx | H18: ImpactLens Pricing › D12 | I18: Contradicted | J18: Low | K18: Published price implies a higher figure: see next row and Open Items O-01.
B19: A14 | C19: Unit economics | D19: ₹ per credit implied by Cloudinary's published price | E19: =Pricing!$C$61 -> 38.001022 | F19: ₹ | G19: competitors.csv | H19: cloudinary row (https://cloudinary.com/pricing, verified 2026-09-29) | I19: Calculated | J19: Medium | K19: $89 for 225 credits at the workbook's FX rate.
B20: A15 | C20: Unit economics | D20: ₹ per AI vision analysis | E20: =Pricing!$C$52 -> 0.9 | F20: ₹ | G20: IMPACTLENS PRICING MODEL.xlsx | H20: ImpactLens Pricing › D13 | I20: Assumption | J20: Low | K20: Labelled 'assumption' in the source; not measured. Token usage is not logged.
B21: A16 | C21: Unit economics | D21: ₹ per report / ₹ per semantic search | E21: 1.00 / 0.50 | F21: ₹ | G21: IMPACTLENS PRICING MODEL.xlsx | H21: ImpactLens Pricing › D13 | I21: Assumption | J21: Low | K21: Search cost holds only while the LLM prompt is capped (120 candidates, Rev. 4).
B22: A17 | C22: Unit economics | D22: Frames sent per video | E22: =Pricing!$C$64 -> 6 | F22: frames | G22: IMPACTLENS PRICING MODEL.xlsx | H22: 'Cost Inputs'!C29 (from src/lib/ai.ts) | I22: Documented | J22: High | K22: Upper bound used for the all-video stress case.
B23: A18 | C23: Unit economics | D23: Gross margin as modelled: Starter / Pro / Enterprise | E23: =TEXT(Pricing!C57,"0.0%")&" / "&TEXT(Pricing!D57,"0.0%")&" / "&TEXT(Pricing!E57,"0.0%") -> 85.6% / 65.2% / 48.7% | F23: % | G23: This workbook | H23: Pricing section 4 | I23: Calculated | J23: Medium | K23: Cost floor only: excludes hosting, support, fees, tax.
B24: A19 | C24: Unit economics | D24: Gross margin at the published Cloudinary price | E24: =TEXT(Pricing!C63,"0.0%")&" / "&TEXT(Pricing!D63,"0.0%")&" / "&TEXT(Pricing!E63,"0.0%") -> 84.2% / 62.7% / 45.7% | F24: % | G24: This workbook | H24: Pricing section 4 | I24: Calculated | J24: Medium
B25: A20 | C25: Unit economics | D25: Gross margin if every analysis is a video (upper bound) | E25: =TEXT(Pricing!C66,"0.0%")&" / "&TEXT(Pricing!D66,"0.0%")&" / "&TEXT(Pricing!E66,"0.0%") -> 84.2% / 6.5% / -66.8% | F25: % | G25: This workbook | H25: Pricing section 4 | I25: Calculated | J25: Low | K25: Stress case; frames are downscaled so the true multiplier is lower but unmeasured.
B26: A21 | C26: Pricing | D26: Phase 2 price ranges (low / high, Starter) | E26: =TEXT(Pricing!C71,"#,##0")&" / "&TEXT(Pricing!C72,"#,##0") -> 4,000 / 5,000 | F26: ₹ / month | G26: IMPACTLENS PRICING MODEL.xlsx | H26: ImpactLens Pricing › D74 | I26: Documented | J26: High
B27: A22 | C27: Pricing | D27: Phase 2 price ranges (low / high, Pro) | E27: =TEXT(Pricing!D71,"#,##0")&" / "&TEXT(Pricing!D72,"#,##0") -> 12,000 / 15,000 | F27: ₹ / month | G27: IMPACTLENS PRICING MODEL.xlsx | H27: ImpactLens Pricing › D75 | I27: Documented | J27: High
B28: A23 | C28: Pricing | D28: Phase 2 price ranges (low / high, Enterprise) | E28: =TEXT(Pricing!E71,"#,##0")&" / "&TEXT(Pricing!E72,"#,##0") -> 29,000 / 39,000 | F28: ₹ / month | G28: IMPACTLENS PRICING MODEL.xlsx | H28: ImpactLens Pricing › D76 | I28: Documented | J28: High
B29: A24 | C29: Pricing | D29: Phase 2 trigger | E29: 50 paying orgs + public API pilot + funder-verification pilots | G29: IMPACTLENS PRICING MODEL.xlsx | H29: ImpactLens Pricing › D72 | I29: Documented | J29: High | K29: Dates: not documented.
B30: A25 | C30: Pricing | D30: Feature entitlements and limits by tier | E30: see Pricing §3 | G30: IMPACTLENS PRICING MODEL.xlsx | H30: ImpactLens Pricing › rows 52–69 | I30: Documented | J30: High | K30: Not enforced in the product (memo U3).
B31: A26 | C31: Pricing | D31: Support level by tier | E31: Email / Email + Chat / Dedicated + SLA | G31: IMPACTLENS PRICING MODEL.xlsx | H31: ImpactLens Pricing › row 69 | I31: Documented | J31: High | K31: SLA terms undefined.
B32: A27 | C32: Pricing | D32: Add-ons, overage, other discounts, free tier | E32: ="Analysis ₹"&'Planning Inputs'!$D$67&", credit ₹"&'Planning Inputs'!$D$68&", seat ₹"&'Planning Inputs'!$D$69&"; 14-day trial; 2-yr prepay "&TEXT('Planning Inputs'!$D$70,"0%") -> Analysis ₹3, credit ₹114, seat ₹500; 14-day trial; 2-yr prepay 5% | G32: Planning Inputs | H32: §3, §8 | I32: Assumption | J32: Low
B33: A28 | C33: Product | D33: Value proposition | E33: Field evidence → AI insight → donor-ready reports | G33: IMPACTLENS PRICING MODEL.xlsx | H33: ImpactLens Pricing › A3, A79 | I33: Documented | J33: High
B34: A29 | C34: Product | D34: Problem, users, goals, functional scope (F1–F13) | E34: see ICP sheet | G34: PRD.md (repo root, outside docs/) | H34: §1–§4 | I34: Documented | J34: High | K34: Outside docs/; the PRD is the only source for personas and product scope.
B35: A30 | C35: Product | D35: Non-goals: general DAM, video editor, donor CRM, multi-region scale | E35: stated | G35: PRD.md (repo root, outside docs/) | H35: §3 | I35: Documented | J35: High | K35: Bounds the GTM: not a DAM or CRM.
B36: A31 | C36: Product | D36: Deployment target undecided (Caddy on a VM or a Vercel-style host) | E36: undecided | G36: PRD.md (repo root, outside docs/) | H36: §7 | I36: Documented | J36: High | K36: Affects hosting cost, headers, proxy, cron.
B37: A32 | C37: GTM | D37: Positioning statement | E37: The report layer for organisations that already have field media… | G37: COMPETITIVE-LANDSCAPE.md | H37: §3 | I37: Hypothesis | J37: Low | K37: Untested with customers.
B38: A33 | C38: GTM | D38: Underserved segments | E38: S5 (small / mid NGOs with a photo backlog); S2; S3 | G38: COMPETITIVE-LANDSCAPE.md | H38: §3 | I38: Hypothesis | J38: Low | K38: No customer interviews exist.
B39: A34 | C39: GTM | D39: Channel / partner ideas (embed widget, import connectors, WhatsApp) | E39: proposed | G39: COMPETITIVE-LANDSCAPE.md | H39: §5 U8, U12, U13 | I39: Hypothesis | J39: Low | K39: Not decided; APIs and terms not checked.
B40: A35 | C40: GTM | D40: Sales motion by tier (self-serve vs sales-led) | E40: inferred from support levels | G40: IMPACTLENS PRICING MODEL.xlsx | H40: row 69 | I40: Assumption | J40: Low
B41: A36 | C41: GTM | D41: Acquisition, marketing and sales channels; geography | E41: India first; content, referral, connector and share-link channels | G41: Planning Inputs | H41: §1; GTM Strategy rows 10–17 | I41: Assumption | J41: Low
B42: A37 | C42: GTM | D42: Time to a searchable asset | E42: < 30 s per image | G42: PRD.md (repo root, outside docs/) | H42: §6 | I42: Documented | J42: High
B43: A38 | C43: GTM | D43: Reports citing ≥ 3 real assets | E43: 100% | G43: PRD.md (repo root, outside docs/) | H43: §6 | I43: Documented | J43: High | K43: Not enforced or measured today (memo U2).
B44: A39 | C44: GTM | D44: Zero cross-tenant reads / writes | E44: 0 | G44: PRD.md (repo root, outside docs/) | H44: §6 | I44: Documented | J44: High
B45: A40 | C45: Revenue | D45: Customer counts, growth, churn, upgrade rates, billing mix | E45: ="Churn "&TEXT('Planning Inputs'!$D$37,"0.0%")&" / "&TEXT('Planning Inputs'!$D$38,"0.0%")&" / "&TEXT('Planning Inputs'!$D$39,"0.0%")&" a month; mix "&TEXT('Planning Inputs'!$D$34,"0%")&" / "&TEXT('Planning Inputs'!$D$35,"0%")&" / "&TEXT('Planning Inputs'!$D$36,"0%") -> Churn 3.0% / 1.5% / 0.7% a month; mix 60% / 30% / 10% | G45: Planning Inputs | H45: §2, §4 | I45: Assumption | J45: Low | K45: Scenario inputs now come from Planning Inputs; churn from public SaaS benchmarks.
B46: A41 | C46: Revenue | D46: CAC, payback, conversion rates | E46: ="Sign-up → paid "&TEXT('Planning Inputs'!$D$23,"0.0%")&"; blended CAC ₹"&TEXT('Revenue Model'!C89,"#,##0") -> Sign-up → paid 10.1%; blended CAC ₹54,812 | G46: Planning Inputs; Revenue Model | H46: §2, §5; Revenue Model D | I46: Assumption | J46: Low
B47: A42 | C47: Revenue | D47: Market size (TAM / SAM / SOM) | E47: ="TAM ₹"&TEXT('Revenue Model'!D98,"#,##0")&" cr / SAM ₹"&TEXT('Revenue Model'!D99,"#,##0")&" cr / SOM ₹"&TEXT('Revenue Model'!D100,"#,##0.0")&" cr" -> TAM ₹310 cr / SAM ₹93 cr / SOM ₹1.9 cr | G47: Planning Inputs; Revenue Model | H47: §7; Revenue Model E | I47: Calculated | J47: Medium | K47: Public org counts (FCRA, National CSR Portal) × assumed reachable shares.
B48: A43 | C48: Revenue | D48: Tax (e.g. GST), payment fees, hosting, support cost | E48: ="GST "&TEXT('Planning Inputs'!$D$50,"0%")&" on top; gateway "&TEXT('Planning Inputs'!$D$51,"0%")&" + GST; hosting ₹"&TEXT('Planning Inputs'!$D$55,"#,##0")&" / mo" -> GST 18% on top; gateway 2% + GST; hosting ₹8,000 / mo | G48: Planning Inputs | H48: §6 | I48: Assumption | J48: Low | K48: GST is collected on top of price, so it is not a cost.
B49: A44 | C49: Competitive | D49: Competitor register: rows / with a verified page | E49: =COUNTA('Competitive Positioning'!B8:B32) -> 25 | F49: rows | G49: competitors.csv | H49: all rows | I49: Documented | J49: See register | K49: Confidence per row on the Competitive Positioning sheet.
B50: A45 | C50: Competitive | D50: Rows verified High confidence | E50: =COUNTIF('Competitive Positioning'!L8:L32,"High") -> 15 | F50: rows | G50: competitors.csv | H50: confidence column | I50: Calculated | J50: High
B51: A46 | C51: Competitive | D51: Rows unverified (Low) or dead | E51: =COUNTIF('Competitive Positioning'!L8:L32,"Low")+COUNTIF('Competitive Positioning'!L8:L32,"Dead") -> 1 | F51: rows | G51: competitors.csv | H51: confidence column | I51: Calculated | J51: High
B52: A47 | C52: Competitive | D52: Competitor prices (USD / month) | E52: see Competitive Positioning | F52: $ | G52: competitors.csv | H52: price_summary; each row's source URL | I52: Documented | J52: High | K52: Read from vendor pages 2026-09-29 through a summarising tool: re-read before external use.

Sheet Open Items
B2: OPEN ITEMS: CONTRADICTIONS AND MISSING INFORMATION
B3: Contradictions are shown with both sides. Gaps that blocked the model now carry a labelled planning assumption from 'Planning Inputs' (Status column); the owner still has to confirm them.
B5: ID | C5: Type | D5: Item | E5: Evidence / where it appears | F5: What is needed to close it | G5: Affects | H5: Status (2026-09-30)
B6: O-01 | C6: Contradiction | D6: Cloudinary cost per credit: ₹34 (model) vs ₹38.0 (published price) | E6: IMPACTLENS PRICING MODEL.xlsx uses ~₹34 per credit but cites $89/mo for 225 credits, which is ₹38.0 at its own 96.07 FX rate (₹42.3 if billed monthly). Cloudinary's page (docs/competitors.csv, verified 2026-09-29) confirms $89 annual / $99 monthly for 225 credits. | F6: Pricing owner decides which Cloudinary plan and billing to model, and which FX rate. | G6: Pricing §4; all margins | H6: Open: owner decision needed.
B7: O-02 | C7: Contradiction | D7: Enterprise tier lists SSO / RBAC / audit log as 'Phase 2', but the tier is priced now | E7: IMPACTLENS PRICING MODEL.xlsx › row 68 ('Phase 2') vs rows 71–77 (those features justify the Phase 2 price rise). Enterprise support also promises an SLA now, while '99.9% uptime SLA' is a Phase 2 item. | F7: Decide what Enterprise includes on day one and remove or date the Phase 2 items from the tier. | G7: Pricing §3, §5 | H7: Open: owner decision needed.
B8: O-03 | C8: Contradiction | D8: 'Unlimited' Enterprise features vs a fixed-allowance cost floor | E8: Enterprise lists unlimited orgs, seats, assets and comparisons, yet COGS assumes 5,000 analyses and 150 credits. Margin is 48.7% as modelled and 45.7% at the published Cloudinary price. | F8: Define bounded units and overage, or accept the risk explicitly. | G8: Pricing §3–4; Revenue Model | H8: Open: owner decision needed.
B9: O-04 | C9: Gap / tension | D9: Geography and currency | E9: Prices are INR-primary with USD 'indicative' (IMPACTLENS PRICING MODEL.xlsx › D7), but the competitor set is priced in USD and no doc names a target geography or region. | F9: State the launch geography and billing currency. | G9: GTM; Pricing | H9: Assumed: India first, INR billing (Planning Inputs §1). Confirm.
B10: O-05 | C10: Contradiction | D10: Semantic search shown as unlimited, costed as ~300 / 1,000 a month | E10: Feature table row 58 is a bare tick; COGS row 22 is a typed ₹180 / ₹650. At ₹1.00 per report and ₹0.50 per search the numbers imply about 300 and 1,000 searches (docs/IMPACTLENS PRICING MODEL.xlsx › 'Cost Inputs' §4). | F10: Define a search allowance per tier. | G10: Pricing §3–4 | H10: Open: owner decision needed.
B11: O-06 | C11: Gap | D11: What counts as one 'analysis' when the media is a video | E11: Video analysis samples up to 6 frames. If every Pro / Enterprise analysis is a video, modelled margin falls to 6.5% and −66.8% (calculated upper bound). | F11: Define the billable unit for video. | G11: Pricing §4 | H11: Open: owner decision needed.
B12: O-07 | C12: Gap | D12: Plan limits are not enforced by the product | E12: There is no plan, quota or overage in the schema; the limits exist only in the workbook (docs/COMPETITIVE-LANDSCAPE.md U3). | F12: Product build after the unit decisions above. | G12: Pricing; Revenue Model | H12: Open: owner decision needed.
B13: O-08 | C13: Missing | D13: Customers, pipeline, growth, churn, upgrade rates, billing mix | E13: None appears in any doc. The Revenue Model scenario inputs are blank on purpose. | F13: Founder / sales input; or a stated planning scenario clearly labelled as an assumption. | G13: Revenue Model | H13: Assumed: sign-ups, funnel, mix, churn and upgrades (Planning Inputs §2–4). Confirm.
B14: O-09 | C14: Missing | D14: Costs outside COGS | E14: Hosting, support (Enterprise promises dedicated support), payment-gateway fees, tax (for example GST on SaaS), the cost of comparisons, campaign copy, scheduled runs and image generation. | F14: Finance / measured usage. | G14: Pricing §4; Revenue Model | H14: Partly assumed: gateway, support, hosting (§6). Comparison and campaign costs still unmeasured.
B15: O-10 | C15: Missing | D15: Acquisition, marketing and sales channels; sales motion; CAC; conversion; market size | E15: The docs have none. Only channel *ideas* exist, as hypotheses in the memo (embed widget, import connectors, WhatsApp). | F15: Founder / GTM lead. | G15: GTM Strategy; ICP | H15: Assumed: channels, motion, CAC ceiling, market size (§1, §5, §7). Confirm.
B16: O-11 | C16: Missing | D16: Definition of 'Impact Evidence Maturity' (Low / Mid / High) | E16: Used to name the three tiers (IMPACTLENS PRICING MODEL.xlsx › row 30); no criteria anywhere, so a buyer cannot self-select. | F16: Write the criteria or replace the label. | G16: ICP; Pricing §2 | H16: Assumed: criteria written from the tier limits (Pricing F13). Confirm.
... B21: O-16 | C21: Provenance note | D21: Two of the three docs were written during the 2026-09-29 audit | E21: docs/COMPETITIVE-LANDSCAPE.md and docs/competitors.csv contain research, recommendations and hypotheses by the auditor, not management decisions. Only IMPACTLENS PRICING MODEL.xlsx is an original planning document. | F21: Treat Hypothesis rows as proposals until the owners confirm. | G21: All sheets | H21: Open: owner decision needed.
